<Drive>
<TestType>Stationary</TestType>
<ChildTestType>rdoStationary</ChildTestType>
<Site>9BH1440A</Site>
<Sector>Beta</Sector>
<Pci>687</Pci>
<Date>2020-02-13</Date>
<Time>17-14-37</Time>

<message-body><rat>LTE</rat><RadioBearerID>1</RadioBearerID><Freq>66786</Freq><PCI>428</PCI><time>23:14:42.297</time><channel>EUTRA-UL-DCCH-Message</channel><event>measurementReport</event><EUTRA-UL-DCCH-Message>    <message>        <c1>            <measurementReport>                <criticalExtensions>                    <c1>                        <measurementReport-r8>                            <measResults>                                <measId>9</measId>                                <measResultPCell>                                    <rsrpResult>53</rsrpResult>                                    <rsrqResult>20</rsrqResult>                                </measResultPCell>                                <measResultNeighCells>                                    <measResultListEUTRA>                                        <EUTRA-MeasResultEUTRA>                                            <physCellId>427</physCellId>                                            <measResult>                                                <rsrpResult>50</rsrpResult>                                                <rsrqResult>11</rsrqResult>                                            </measResult>                                        </EUTRA-MeasResultEUTRA>                                    </measResultListEUTRA>                                </measResultNeighCells>                            </measResults>                        </measurementReport-r8>                    </c1>                </criticalExtensions>            </measurementReport>        </c1>    </message></EUTRA-UL-DCCH-Message></message-body>
<message-body><rat>LTE</rat><RadioBearerID>1</RadioBearerID><Freq>66786</Freq><PCI>428</PCI><time>23:14:52.541</time><channel>EUTRA-UL-DCCH-Message</channel><event>measurementReport</event><EUTRA-UL-DCCH-Message>    <message>        <c1>            <measurementReport>                <criticalExtensions>                    <c1>                        <measurementReport-r8>                            <measResults>                                <measId>9</measId>                                <measResultPCell>                                    <rsrpResult>54</rsrpResult>                                    <rsrqResult>24</rsrqResult>                                </measResultPCell>                                <measResultNeighCells>                                    <measResultListEUTRA>                                        <EUTRA-MeasResultEUTRA>                                            <physCellId>427</physCellId>                                            <measResult>                                                <rsrpResult>49</rsrpResult>                                                <rsrqResult>14</rsrqResult>                                            </measResult>                                        </EUTRA-MeasResultEUTRA>                                    </measResultListEUTRA>                                </measResultNeighCells>                            </measResults>                        </measurementReport-r8>                    </c1>                </criticalExtensions>            </measurementReport>        </c1>    </message></EUTRA-UL-DCCH-Message></message-body>
<message-body><rat>LTE</rat><RadioBearerID>1</RadioBearerID><Freq>66786</Freq><PCI>428</PCI><time>23:15:13.021</time><channel>EUTRA-UL-DCCH-Message</channel><event>measurementReport</event><EUTRA-UL-DCCH-Message>    <message>        <c1>            <measurementReport>                <criticalExtensions>                    <c1>                        <measurementReport-r8>                            <measResults>                                <measId>9</measId>                                <measResultPCell>                                    <rsrpResult>52</rsrpResult>                                    <rsrqResult>20</rsrqResult>                                </measResultPCell>                                <measResultNeighCells>                                    <measResultListEUTRA>                                        <EUTRA-MeasResultEUTRA>                                            <physCellId>427</physCellId>                                            <measResult>                                                <rsrpResult>49</rsrpResult>                                                <rsrqResult>10</rsrqResult>                                            </measResult>                                        </EUTRA-MeasResultEUTRA>                                    </measResultListEUTRA>                                </measResultNeighCells>                            </measResults>                        </measurementReport-r8>                    </c1>                </criticalExtensions>            </measurementReport>        </c1>    </message></EUTRA-UL-DCCH-Message></message-body>
<message-body><rat>LTE</rat><RadioBearerID>1</RadioBearerID><Freq>66786</Freq><PCI>428</PCI><time>23:15:23.261</time><channel>EUTRA-UL-DCCH-Message</channel><event>measurementReport</event><EUTRA-UL-DCCH-Message>    <message>        <c1>            <measurementReport>                <criticalExtensions>                    <c1>                        <measurementReport-r8>                            <measResults>                                <measId>9</measId>                                <measResultPCell>                                    <rsrpResult>52</rsrpResult>                                    <rsrqResult>20</rsrqResult>                                </measResultPCell>                                <measResultNeighCells>                                    <measResultListEUTRA>                                        <EUTRA-MeasResultEUTRA>                                            <physCellId>427</physCellId>                                            <measResult>                                                <rsrpResult>49</rsrpResult>                                                <rsrqResult>12</rsrqResult>                                            </measResult>                                        </EUTRA-MeasResultEUTRA>                                    </measResultListEUTRA>                                </measResultNeighCells>                            </measResults>                        </measurementReport-r8>                    </c1>                </criticalExtensions>            </measurementReport>        </c1>    </message></EUTRA-UL-DCCH-Message></message-body>
<message-body><rat>LTE</rat><RadioBearerID>0</RadioBearerID><Freq>66786</Freq><PCI>428</PCI><time>23:15:32.435</time><channel>EUTRA-PCCH-Message</channel><event>paging</event><EUTRA-PCCH-Message>    <message>        <c1>            <paging>                <pagingRecordList>                    <EUTRA-PagingRecord>                        <ue-Identity>                            <s-TMSI>                                <mmec>                                    01101110                                </mmec>                                <m-TMSI>                                    11000101111100000010000100000010                                </m-TMSI>                            </s-TMSI>                        </ue-Identity>                        <cn-Domain><ps/></cn-Domain>                    </EUTRA-PagingRecord>                </pagingRecordList>            </paging>        </c1>    </message></EUTRA-PCCH-Message></message-body>
<message-body><rat>LTE</rat><RadioBearerID>1</RadioBearerID><Freq>66786</Freq><PCI>428</PCI><time>23:15:33.547</time><channel>EUTRA-UL-DCCH-Message</channel><event>measurementReport</event><EUTRA-UL-DCCH-Message>    <message>        <c1>            <measurementReport>                <criticalExtensions>                    <c1>                        <measurementReport-r8>                            <measResults>                                <measId>9</measId>                                <measResultPCell>                                    <rsrpResult>52</rsrpResult>                                    <rsrqResult>23</rsrqResult>                                </measResultPCell>                                <measResultNeighCells>                                    <measResultListEUTRA>                                        <EUTRA-MeasResultEUTRA>                                            <physCellId>427</physCellId>                                            <measResult>                                                <rsrpResult>49</rsrpResult>                                                <rsrqResult>12</rsrqResult>                                            </measResult>                                        </EUTRA-MeasResultEUTRA>                                    </measResultListEUTRA>                                </measResultNeighCells>                            </measResults>                        </measurementReport-r8>                    </c1>                </criticalExtensions>            </measurementReport>        </c1>    </message></EUTRA-UL-DCCH-Message></message-body>
<message-body><rat>LTE</rat><RadioBearerID>0</RadioBearerID><Freq>66786</Freq><PCI>428</PCI><time>23:15:34.995</time><channel>EUTRA-PCCH-Message</channel><event>paging</event><EUTRA-PCCH-Message>    <message>        <c1>            <paging>                <pagingRecordList>                    <EUTRA-PagingRecord>                        <ue-Identity>                            <s-TMSI>                                <mmec>                                    01101100                                </mmec>                                <m-TMSI>                                    11000100111001001110011101110011                                </m-TMSI>                            </s-TMSI>                        </ue-Identity>                        <cn-Domain><ps/></cn-Domain>                    </EUTRA-PagingRecord>                </pagingRecordList>            </paging>        </c1>    </message></EUTRA-PCCH-Message></message-body>

</Drive>
