{"drive":{"test-cat":"Stationary","test-type":"DL","site":"BJTest123","net-mode":"LTE","band":"LTE 1900","carrier":"1100","sector":"Alpha","time":"07-25-2017-04-53-51-PM","message-body":[{"time":"1501099421","channel":"PCCH-Message","event":"paging","PCCH-Message":{"message":{"c1":{"paging":{"pagingRecordList":{"PagingRecord":{"ue-Identity":{"s-TMSI":{"mmec":"\n                                    00111000\n                                ","m-TMSI":"\n                                    11111011000010100101111001011110\n                                "}},"cn-Domain":{"ps":null}}}}}}},"hex":"3C6D6573736167652D626F64"},{"time":"1501099421","channel":"DL-DCCH-Message","event":"csfbParametersResponseCDMA2000","DL-DCCH-Message":{"message":{"c1":{"csfbParametersResponseCDMA2000":{"rrc-TransactionIdentifier":"0","criticalExtensions":{"csfbParametersResponseCDMA2000-r8":{"rand":"\n                            00000000000000000000111010000000\n                        ","mobilityParameters":"1F 61 4B CB C0 38 00"}}}}}},"hex":"3C6D6573736167652D626F"},{"time":"1501099422","channel":"PCCH-Message","event":"paging","PCCH-Message":{"message":{"c1":{"paging":{"pagingRecordList":{"PagingRecord":{"ue-Identity":{"s-TMSI":{"mmec":"\n                                    00111000\n                                ","m-TMSI":"\n                                    11000010000101111101010111010000\n                                "}},"cn-Domain":{"cs":null}}}}}}},"hex":"3C6D6573736167652D626F64"},{"time":"1501099422","channel":"PCCH-Message","event":"paging","PCCH-Message":{"message":{"c1":{"paging":{"pagingRecordList":{"PagingRecord":{"ue-Identity":{"s-TMSI":{"mmec":"\n                                    00111000\n                                ","m-TMSI":"\n                                    11000011000001011111001010101001\n                                "}},"cn-Domain":{"ps":null}}}}}}},"hex":"3C6D6573736167652D626F64"},{"time":"1501099423","channel":"PCCH-Message","event":"paging","PCCH-Message":{"message":{"c1":{"paging":{"pagingRecordList":{"PagingRecord":[{"ue-Identity":{"s-TMSI":{"mmec":"\n                                    00111000\n                                ","m-TMSI":"\n                                    11000010000101110100010011010011\n                                "}},"cn-Domain":{"ps":null}},{"ue-Identity":{"s-TMSI":{"mmec":"\n                                    00111000\n                                ","m-TMSI":"\n                                    11000010000001111101110100000010\n                                "}},"cn-Domain":{"ps":null}}]}}}}},"hex":"3C6D6573736167652D626F64793E3C74696D65"},{"time":"1501099424","channel":"PCCH-Message","event":"paging","PCCH-Message":{"message":{"c1":{"paging":{"pagingRecordList":{"PagingRecord":{"ue-Identity":{"s-TMSI":{"mmec":"\n                                    00111000\n                                ","m-TMSI":"\n                                    11100010000101010101100010010100\n                                "}},"cn-Domain":{"ps":null}}}}}}},"hex":"3C6D6573736167652D626F64"},{"time":"1501099424","channel":"PCCH-Message","event":"paging","PCCH-Message":{"message":{"c1":{"paging":{"pagingRecordList":{"PagingRecord":[{"ue-Identity":{"s-TMSI":{"mmec":"\n                                    00111000\n                                ","m-TMSI":"\n                                    11100101000010100100110011110110\n                                "}},"cn-Domain":{"ps":null}},{"ue-Identity":{"s-TMSI":{"mmec":"\n                                    00111000\n                                ","m-TMSI":"\n                                    11101010000010001101000110101011\n                                "}},"cn-Domain":{"ps":null}}]}}}}},"hex":"3C6D6573736167652D626F64793E3C74696D65"},{"time":"1501099424","channel":"PCCH-Message","event":"paging","PCCH-Message":{"message":{"c1":{"paging":{"pagingRecordList":{"PagingRecord":{"ue-Identity":{"s-TMSI":{"mmec":"\n                                    00111000\n                                ","m-TMSI":"\n                                    11011110000000011011010111101001\n                                "}},"cn-Domain":{"ps":null}}}}}}},"hex":"3C6D6573736167652D626F64"},{"time":"1501099424","channel":"PCCH-Message","event":"paging","PCCH-Message":{"message":{"c1":{"paging":{"pagingRecordList":{"PagingRecord":{"ue-Identity":{"s-TMSI":{"mmec":"\n                                    00111000\n                                ","m-TMSI":"\n                                    11011110000000011011010111101001\n                                "}},"cn-Domain":{"ps":null}}}}}}},"hex":"3C6D6573736167652D626F64"},{"time":"1501099425","channel":"PCCH-Message","event":"paging","PCCH-Message":{"message":{"c1":{"paging":{"pagingRecordList":{"PagingRecord":{"ue-Identity":{"s-TMSI":{"mmec":"\n                                    00111000\n                                ","m-TMSI":"\n                                    11011110000000011011010111101001\n                                "}},"cn-Domain":{"ps":null}}}}}}},"hex":"3C6D6573736167652D626F64"},{"time":"1501099426","channel":"PCCH-Message","event":"paging","PCCH-Message":{"message":{"c1":{"paging":{"pagingRecordList":{"PagingRecord":{"ue-Identity":{"s-TMSI":{"mmec":"\n                                    00111000\n                                ","m-TMSI":"\n                                    11011110000000011011010111101001\n                                "}},"cn-Domain":{"ps":null}}}}}}},"hex":"3C6D6573736167652D626F64"},{"time":"1344732454","channel":"DL-DCCH-Message","event":"csfbParametersResponseCDMA2000","DL-DCCH-Message":{"message":{"c1":{"csfbParametersResponseCDMA2000":{"rrc-TransactionIdentifier":"0","criticalExtensions":{"criticalExtensionsFuture":""}}}}},"hex":"3C6D6573736167"},{"time":"1501099430","channel":"PCCH-Message","event":"paging","PCCH-Message":{"message":{"c1":{"paging":{"pagingRecordList":{"PagingRecord":{"ue-Identity":{"s-TMSI":{"mmec":"\n                                    00111000\n                                ","m-TMSI":"\n                                    11010010000010110001011110101100\n                                "}},"cn-Domain":{"ps":null}}}}}}},"hex":"3C6D6573736167652D626F64"},{"time":"1501099430","channel":"PCCH-Message","event":"paging","PCCH-Message":{"message":{"c1":{"paging":{"pagingRecordList":{"PagingRecord":[{"ue-Identity":{"s-TMSI":{"mmec":"\n                                    00111000\n                                ","m-TMSI":"\n                                    11100010000101010000011001010101\n                                "}},"cn-Domain":{"ps":null}},{"ue-Identity":{"s-TMSI":{"mmec":"\n                                    00111000\n                                ","m-TMSI":"\n                                    11000010000001011011101001110101\n                                "}},"cn-Domain":{"ps":null}},{"ue-Identity":{"s-TMSI":{"mmec":"\n                                    00111000\n                                ","m-TMSI":"\n                                    11000111000000010101110100011011\n                                "}},"cn-Domain":{"ps":null}},{"ue-Identity":{"s-TMSI":{"mmec":"\n                                    00111000\n                                ","m-TMSI":"\n                                    11010010000111000111110101011101\n                                "}},"cn-Domain":{"cs":null}}]}}}}},"hex":"3C6D6573736167652D626F64793E3C74696D653E313530313039393433303C2F74696D"},{"time":"1501099430","channel":"PCCH-Message","event":"paging","PCCH-Message":{"message":{"c1":{"paging":{"pagingRecordList":{"PagingRecord":[{"ue-Identity":{"s-TMSI":{"mmec":"\n                                    00111000\n                                ","m-TMSI":"\n                                    11001101000101011001100001010000\n                                "}},"cn-Domain":{"cs":null}},{"ue-Identity":{"s-TMSI":{"mmec":"\n                                    00111000\n                                ","m-TMSI":"\n                                    11000001000000110000000101100000\n                                "}},"cn-Domain":{"ps":null}},{"ue-Identity":{"s-TMSI":{"mmec":"\n                                    00111000\n                                ","m-TMSI":"\n                                    11100010000100010001001111110010\n                                "}},"cn-Domain":{"ps":null}}]}}}}},"hex":"3C6D6573736167652D626F64793E3C74696D653E31353031303939"},{"time":"1344732864","channel":"PCCH-Message","event":"paging","PCCH-Message":{"message":{"c1":{"paging":""}}},"hex":"3C6D65"},{"time":"1501099431","channel":"PCCH-Message","event":"paging","PCCH-Message":{"message":{"c1":{"paging":""}}},"hex":"3C6D65"},{"time":"1501099431","channel":"PCCH-Message","event":"paging","PCCH-Message":{"message":{"c1":{"paging":{"pagingRecordList":{"PagingRecord":[{"ue-Identity":{"s-TMSI":{"mmec":"\n                                    00111000\n                                ","m-TMSI":"\n                                    11100010000011000000101100010011\n                                "}},"cn-Domain":{"ps":null}},{"ue-Identity":{"s-TMSI":{"mmec":"\n                                    00111000\n                                ","m-TMSI":"\n                                    11000010000100010100110110000011\n                                "}},"cn-Domain":{"ps":null}}]}}}}},"hex":"3C6D6573736167652D626F64793E3C74696D65"},{"time":"1501099431","channel":"DL-DCCH-Message","event":"csfbParametersResponseCDMA2000","DL-DCCH-Message":{"message":{"c1":{"csfbParametersResponseCDMA2000":{"rrc-TransactionIdentifier":"0","criticalExtensions":{"csfbParametersResponseCDMA2000-r8":{"rand":"\n                            00000000000000000001101010000001\n                        ","mobilityParameters":"1C 41 81 62 60 71 84"}}}}}},"hex":"3C6D6573736167652D626F"},{"time":"1344730372","channel":"DL-DCCH-Message","event":"spare3","DL-DCCH-Message":{"message":{"c1":{"spare3":""}}},"hex":"3C6D65"},{"time":"1344730372","channel":"DL-DCCH-Message","event":"spare3","DL-DCCH-Message":{"message":{"c1":{"spare3":""}}},"hex":"3C6D65"},{"time":"1344730454","channel":"DL-DCCH-Message","event":"spare3","DL-DCCH-Message":{"message":{"c1":{"spare3":""}}},"hex":"3C6D65"},{"time":"1344730454","channel":"DL-DCCH-Message","event":"csfbParametersResponseCDMA2000","DL-DCCH-Message":{"message":{"c1":{"csfbParametersResponseCDMA2000":{"rrc-TransactionIdentifier":"0","criticalExtensions":{"csfbParametersResponseCDMA2000-r8":{"rand":"\n                            00000000000000000000000000000000\n                        ","mobilityParameters":""}}}}}},"hex":"3C6D6573736167652D62"},{"time":"1344730454","channel":"DL-DCCH-Message","event":"csfbParametersResponseCDMA2000","DL-DCCH-Message":{"message":{"c1":{"csfbParametersResponseCDMA2000":{"rrc-TransactionIdentifier":"0","criticalExtensions":{"criticalExtensionsFuture":""}}}}},"hex":"3C6D6573736167"},{"time":"1501099433","channel":"PCCH-Message","event":"paging","PCCH-Message":{"message":{"c1":{"paging":{"pagingRecordList":{"PagingRecord":[{"ue-Identity":{"s-TMSI":{"mmec":"\n                                    00111000\n                                ","m-TMSI":"\n                                    11111000000001111000110000011010\n                                "}},"cn-Domain":{"ps":null}},{"ue-Identity":{"s-TMSI":{"mmec":"\n                                    00111000\n                                ","m-TMSI":"\n                                    11100010000001111011011001000100\n                                "}},"cn-Domain":{"ps":null}}]}}}}},"hex":"3C6D6573736167652D626F64793E3C74696D65"},{"time":"1501099434","channel":"PCCH-Message","event":"paging","PCCH-Message":{"message":{"c1":{"paging":{"pagingRecordList":{"PagingRecord":{"ue-Identity":{"s-TMSI":{"mmec":"\n                                    00111000\n                                ","m-TMSI":"\n                                    11010000000110001100000101000110\n                                "}},"cn-Domain":{"ps":null}}}}}}},"hex":"3C6D6573736167652D626F64"},{"time":"1501099434","channel":"PCCH-Message","event":"paging","PCCH-Message":{"message":{"c1":{"paging":{"pagingRecordList":{"PagingRecord":{"ue-Identity":{"s-TMSI":{"mmec":"\n                                    00111000\n                                ","m-TMSI":"\n                                    11010000000110001100000101000110\n                                "}},"cn-Domain":{"ps":null}}}}}}},"hex":"3C6D6573736167652D626F64"},{"time":"1501099435","channel":"PCCH-Message","event":"paging","PCCH-Message":{"message":{"c1":{"paging":{"pagingRecordList":{"PagingRecord":{"ue-Identity":{"s-TMSI":{"mmec":"\n                                    00111000\n                                ","m-TMSI":"\n                                    11010000000110001100000101000110\n                                "}},"cn-Domain":{"ps":null}}}}}}},"hex":"3C6D6573736167652D626F64"},{"time":"1501099435","channel":"PCCH-Message","event":"paging","PCCH-Message":{"message":{"c1":{"paging":{"pagingRecordList":{"PagingRecord":{"ue-Identity":{"s-TMSI":{"mmec":"\n                                    00111000\n                                ","m-TMSI":"\n                                    11010000000110001100000101000110\n                                "}},"cn-Domain":{"ps":null}}}}}}},"hex":"3C6D6573736167652D626F64"},{"time":"1344734174","channel":"DL-DCCH-Message","event":"csfbParametersResponseCDMA2000","DL-DCCH-Message":{"message":{"c1":{"csfbParametersResponseCDMA2000":{"rrc-TransactionIdentifier":"0","criticalExtensions":{"criticalExtensionsFuture":""}}}}},"hex":"3C6D6573736167"},{"time":"1501099436","channel":"PCCH-Message","event":"paging","PCCH-Message":{"message":{"c1":{"paging":{"pagingRecordList":{"PagingRecord":{"ue-Identity":{"s-TMSI":{"mmec":"\n                                    00111000\n                                ","m-TMSI":"\n                                    11100010000001100101011010001111\n                                "}},"cn-Domain":{"ps":null}}}}}}},"hex":"3C6D6573736167652D626F64"},{"time":"1501099437","channel":"PCCH-Message","event":"paging","PCCH-Message":{"message":{"c1":{"paging":{"pagingRecordList":{"PagingRecord":{"ue-Identity":{"s-TMSI":{"mmec":"\n                                    00111000\n                                ","m-TMSI":"\n                                    11100010000001100101011010001111\n                                "}},"cn-Domain":{"ps":null}}}}}}},"hex":"3C6D6573736167652D626F64"},{"time":"1501099438","channel":"PCCH-Message","event":"paging","PCCH-Message":{"message":{"c1":{"paging":{"pagingRecordList":{"PagingRecord":{"ue-Identity":{"s-TMSI":{"mmec":"\n                                    00111000\n                                ","m-TMSI":"\n                                    11100010000001100101011010001111\n                                "}},"cn-Domain":{"ps":null}}}}}}},"hex":"3C6D6573736167652D626F64"},{"time":"1501099439","channel":"PCCH-Message","event":"paging","PCCH-Message":{"message":{"c1":{"paging":{"pagingRecordList":{"PagingRecord":{"ue-Identity":{"s-TMSI":{"mmec":"\n                                    00111000\n                                ","m-TMSI":"\n                                    11100010000001100101011010001111\n                                "}},"cn-Domain":{"ps":null}}}}}}},"hex":"3C6D6573736167652D626F64"},{"time":"1501099440","channel":"PCCH-Message","event":"paging","PCCH-Message":{"message":{"c1":{"paging":{"pagingRecordList":{"PagingRecord":{"ue-Identity":{"s-TMSI":{"mmec":"\n                                    00111000\n                                ","m-TMSI":"\n                                    11100010000001100101011010001111\n                                "}},"cn-Domain":{"ps":null}}}}}}},"hex":"3C6D6573736167652D626F64"},{"time":"1344735157","channel":"DL-DCCH-Message","event":"ueCapabilityEnquiry","DL-DCCH-Message":{"message":{"c1":{"ueCapabilityEnquiry":{"rrc-TransactionIdentifier":"2","criticalExtensions":{"c1":{"spare1":""}}}}}},"hex":"3C6D6573736167"},{"time":"1501099440","channel":"PCCH-Message","event":"paging","PCCH-Message":{"message":{"c1":{"paging":{"pagingRecordList":{"PagingRecord":[{"ue-Identity":{"s-TMSI":{"mmec":"\n                                    00111000\n                                ","m-TMSI":"\n                                    11000001000001110000000101100000\n                                "}},"cn-Domain":{"ps":null}},{"ue-Identity":{"s-TMSI":{"mmec":"\n                                    00111000\n                                ","m-TMSI":"\n                                    11010010000001001001100011111000\n                                "}},"cn-Domain":{"ps":null}}]}}}}},"hex":"3C6D6573736167652D626F64793E3C74696D65"},{"time":"1501099440","channel":"PCCH-Message","event":"paging","PCCH-Message":{"message":{"c1":{"paging":{"pagingRecordList":{"PagingRecord":{"ue-Identity":{"s-TMSI":{"mmec":"\n                                    00111000\n                                ","m-TMSI":"\n                                    11110110000001100011100010000000\n                                "}},"cn-Domain":{"ps":null}}}}}}},"hex":"3C6D6573736167652D626F64"},{"time":"1501099440","channel":"PCCH-Message","event":"paging","PCCH-Message":{"message":{"c1":{"paging":{"pagingRecordList":{"PagingRecord":{"ue-Identity":{"s-TMSI":{"mmec":"\n                                    00111000\n                                ","m-TMSI":"\n                                    11111110000001111101010111011100\n                                "}},"cn-Domain":{"cs":null}}}}}}},"hex":"3C6D6573736167652D626F64"},{"time":"1344735485","channel":"DL-DCCH-Message","event":"dlInformationTransfer","DL-DCCH-Message":{"message":{"c1":{"dlInformationTransfer":{"rrc-TransactionIdentifier":"1","criticalExtensions":{"criticalExtensionsFuture":""}}}}},"hex":"3C6D6573736167"},{"time":"1501099441","channel":"PCCH-Message","event":"paging","PCCH-Message":{"message":{"c1":{"paging":{"pagingRecordList":{"PagingRecord":{"ue-Identity":{"s-TMSI":{"mmec":"\n                                    00111000\n                                ","m-TMSI":"\n                                    11000010000111010010010101100101\n                                "}},"cn-Domain":{"ps":null}}}}}}},"hex":"3C6D6573736167652D626F64"},{"time":"1501099441","channel":"PCCH-Message","event":"paging","PCCH-Message":{"message":{"c1":{"paging":""}}},"hex":"3C6D65"},{"time":"1344735567","channel":"DL-DCCH-Message","event":"csfbParametersResponseCDMA2000","DL-DCCH-Message":{"message":{"c1":{"csfbParametersResponseCDMA2000":{"rrc-TransactionIdentifier":"0","criticalExtensions":{"criticalExtensionsFuture":""}}}}},"hex":"3C6D6573736167"},{"time":"1501099442","channel":"PCCH-Message","event":"paging","PCCH-Message":{"message":{"c1":{"paging":{"pagingRecordList":{"PagingRecord":{"ue-Identity":{"s-TMSI":{"mmec":"\n                                    00111000\n                                ","m-TMSI":"\n                                    11001001000010111000011110001011\n                                "}},"cn-Domain":{"ps":null}}}}}}},"hex":"3C6D6573736167652D626F64"},{"time":"1501099442","channel":"UL-DCCH-Message","event":"csfbParametersRequestCDMA2000","UL-DCCH-Message":{"message":{"c1":{"csfbParametersRequestCDMA2000":{"criticalExtensions":{"csfbParametersRequestCDMA2000-r8":""}}}}},"hex":"3C6D65737361"},{"time":"1344735812","channel":"DL-DCCH-Message","event":"csfbParametersResponseCDMA2000","DL-DCCH-Message":{"message":{"c1":{"csfbParametersResponseCDMA2000":{"rrc-TransactionIdentifier":"0","criticalExtensions":{"criticalExtensionsFuture":""}}}}},"hex":"3C6D6573736167"},{"time":"1344735894","channel":"DL-DCCH-Message","event":"messageClassExtension","DL-DCCH-Message":{"message":{"messageClassExtension":""}},"hex":"3C6D65"},{"time":"1501099443","channel":"PCCH-Message","event":"paging","PCCH-Message":{"message":{"c1":{"paging":{"pagingRecordList":{"PagingRecord":[{"ue-Identity":{"s-TMSI":{"mmec":"\n                                    00111000\n                                ","m-TMSI":"\n                                    11000010000010101111000001011100\n                                "}},"cn-Domain":{"ps":null}},{"ue-Identity":{"s-TMSI":{"mmec":"\n                                    00111000\n                                ","m-TMSI":"\n                                    11000011000000111001100001011100\n                                "}},"cn-Domain":{"ps":null}}]}}}}},"hex":"3C6D6573736167652D626F64793E3C74696D65"},{"time":"1501099443","channel":"PCCH-Message","event":"paging","PCCH-Message":{"message":{"c1":{"paging":{"pagingRecordList":{"PagingRecord":{"ue-Identity":{"s-TMSI":{"mmec":"\n                                    00111000\n                                ","m-TMSI":"\n                                    11000010000110100001000100110000\n                                "}},"cn-Domain":{"ps":null}}}}}}},"hex":"3C6D6573736167652D626F64"},{"time":"1501099444","channel":"PCCH-Message","event":"paging","PCCH-Message":{"message":{"c1":{"paging":{"pagingRecordList":{"PagingRecord":{"ue-Identity":{"s-TMSI":{"mmec":"\n                                    00111000\n                                ","m-TMSI":"\n                                    11000010000110100001000100110000\n                                "}},"cn-Domain":{"ps":null}}}}}}},"hex":"3C6D6573736167652D626F64"},{"time":"1344736632","channel":"DL-DCCH-Message","event":"messageClassExtension","DL-DCCH-Message":{"message":{"messageClassExtension":""}},"hex":"3C6D65"},{"time":"1501099446","channel":"PCCH-Message","event":"paging","PCCH-Message":{"message":{"c1":{"paging":{"pagingRecordList":{"PagingRecord":[{"ue-Identity":{"s-TMSI":{"mmec":"\n                                    00111000\n                                ","m-TMSI":"\n                                    11010010000011100010000110111001\n                                "}},"cn-Domain":{"ps":null}},{"ue-Identity":{"s-TMSI":{"mmec":"\n                                    00111000\n                                ","m-TMSI":"\n                                    11100010000001111011011001000100\n                                "}},"cn-Domain":{"ps":null}},{"ue-Identity":{"s-TMSI":{"mmec":"\n                                    00111000\n                                ","m-TMSI":"\n                                    11010010000001011101010101110001\n                                "}},"cn-Domain":{"ps":null}}]}}}}},"hex":"3C6D6573736167652D626F64793E3C74696D653E31353031303939"},{"time":"1501099446","channel":"PCCH-Message","event":"paging","PCCH-Message":{"message":{"c1":{"paging":{"pagingRecordList":{"PagingRecord":{"ue-Identity":{"s-TMSI":{"mmec":"\n                                    00111000\n                                ","m-TMSI":"\n                                    11101011000011001011111111010100\n                                "}},"cn-Domain":{"ps":null}}}}}}},"hex":"3C6D6573736167652D626F64"},{"time":"1501099447","channel":"PCCH-Message","event":"paging","PCCH-Message":{"message":{"c1":{"paging":{"pagingRecordList":{"PagingRecord":{"ue-Identity":{"s-TMSI":{"mmec":"\n                                    00111000\n                                ","m-TMSI":"\n                                    11101011000011001011111111010100\n                                "}},"cn-Domain":{"ps":null}}}}}}},"hex":"3C6D6573736167652D626F64"},{"time":"1344737041","channel":"DL-DCCH-Message","event":"messageClassExtension","DL-DCCH-Message":{"message":{"messageClassExtension":""}},"hex":"3C6D65"},{"time":"1501099447","channel":"PCCH-Message","event":"paging","PCCH-Message":{"message":{"c1":{"paging":{"pagingRecordList":{"PagingRecord":{"ue-Identity":{"s-TMSI":{"mmec":"\n                                    00111000\n                                ","m-TMSI":"\n                                    11010010000011100001101101111001\n                                "}},"cn-Domain":{"ps":null}}}}}}},"hex":"3C6D6573736167652D626F64"},{"time":"1501099448","channel":"PCCH-Message","event":"paging","PCCH-Message":{"message":{"c1":{"paging":{"pagingRecordList":{"PagingRecord":[{"ue-Identity":{"s-TMSI":{"mmec":"\n                                    00111000\n                                ","m-TMSI":"\n                                    11100100000001111001110001000110\n                                "}},"cn-Domain":{"ps":null}},{"ue-Identity":{"s-TMSI":{"mmec":"\n                                    00111000\n                                ","m-TMSI":"\n                                    11101011000000010111110101011110\n                                "}},"cn-Domain":{"cs":null}}]}}}}},"hex":"3C6D6573736167652D626F64793E3C74696D65"},{"time":"1501099449","channel":"PCCH-Message","event":"paging","PCCH-Message":{"message":{"c1":{"paging":{"pagingRecordList":{"PagingRecord":{"ue-Identity":{"s-TMSI":{"mmec":"\n                                    00111000\n                                ","m-TMSI":"\n                                    11000001000000100000000101100000\n                                "}},"cn-Domain":{"ps":null}}}}}}},"hex":"3C6D6573736167652D626F64"},{"time":"1501099449","channel":"PCCH-Message","event":"paging","PCCH-Message":{"message":{"c1":{"paging":{"pagingRecordList":{"PagingRecord":{"ue-Identity":{"s-TMSI":{"mmec":"\n                                    00111000\n                                ","m-TMSI":"\n                                    11000001000000100000000101100000\n                                "}},"cn-Domain":{"ps":null}}}}}}},"hex":"3C6D6573736167652D626F64"},{"time":"1344737615","channel":"DL-DCCH-Message","event":"csfbParametersResponseCDMA2000","DL-DCCH-Message":{"message":{"c1":{"csfbParametersResponseCDMA2000":{"rrc-TransactionIdentifier":"0","criticalExtensions":{"criticalExtensionsFuture":""}}}}},"hex":"3C6D6573736167"},{"time":"1501099450","channel":"PCCH-Message","event":"paging","PCCH-Message":{"message":{"c1":{"paging":{"pagingRecordList":{"PagingRecord":[{"ue-Identity":{"s-TMSI":{"mmec":"\n                                    00111000\n                                ","m-TMSI":"\n                                    11011100000100111100001110101110\n                                "}},"cn-Domain":{"ps":null}},{"ue-Identity":{"s-TMSI":{"mmec":"\n                                    00111000\n                                ","m-TMSI":"\n                                    11011000000111110100101111010111\n                                "}},"cn-Domain":{"ps":null}}]}}}}},"hex":"3C6D6573736167652D626F64793E3C74696D65"},{"time":"1501099451","channel":"PCCH-Message","event":"paging","PCCH-Message":{"message":{"c1":{"paging":{"pagingRecordList":{"PagingRecord":[{"ue-Identity":{"s-TMSI":{"mmec":"\n                                    00111000\n                                ","m-TMSI":"\n                                    11011100000100111100001110101110\n                                "}},"cn-Domain":{"ps":null}},{"ue-Identity":{"s-TMSI":{"mmec":"\n                                    00111000\n                                ","m-TMSI":"\n                                    11011000000111110100101111010111\n                                "}},"cn-Domain":{"ps":null}}]}}}}},"hex":"3C6D6573736167652D626F64793E3C74696D65"},{"time":"1501099451","channel":"PCCH-Message","event":"paging","PCCH-Message":{"message":{"c1":{"paging":""}}},"hex":"3C6D65"},{"time":"1501099452","channel":"PCCH-Message","event":"paging","PCCH-Message":{"message":{"c1":{"paging":{"pagingRecordList":{"PagingRecord":{"ue-Identity":{"s-TMSI":{"mmec":"\n                                    00111000\n                                ","m-TMSI":"\n                                    11100010000001111011011001000100\n                                "}},"cn-Domain":{"ps":null}}}}}}},"hex":"3C6D6573736167652D626F64"},{"time":"1501099452","channel":"DL-DCCH-Message","event":"csfbParametersResponseCDMA2000","DL-DCCH-Message":{"message":{"c1":{"csfbParametersResponseCDMA2000":{"rrc-TransactionIdentifier":"0","criticalExtensions":{"csfbParametersResponseCDMA2000-r8":{"rand":"\n                            00000000000000000000111010000000\n                        ","mobilityParameters":"1C 40 F6 C8 81 28 AC"}}}}}},"hex":"3C6D6573736167652D626F"},{"time":"1501099452","channel":"PCCH-Message","event":"paging","PCCH-Message":{"message":{"c1":{"paging":{"pagingRecordList":{"PagingRecord":{"ue-Identity":{"s-TMSI":{"mmec":"\n                                    00111000\n                                ","m-TMSI":"\n                                    11111011000000111110001010000111\n                                "}},"cn-Domain":{"ps":null}}}}}}},"hex":"3C6D6573736167652D626F64"},{"time":"1501099452","channel":"UL-DCCH-Message","event":"csfbParametersRequestCDMA2000","UL-DCCH-Message":{"message":{"c1":{"csfbParametersRequestCDMA2000":{"criticalExtensions":{"csfbParametersRequestCDMA2000-r8":""}}}}},"hex":"3C6D65737361"},{"time":"1501099453","channel":"PCCH-Message~","event":"paging","PCCH-Message":{"message":{"c1":{"paging":{"pagingRecordList":{"PagingRecord":{"ue-Identity":{"s-TMSI":{"mmec":"\n                                    00111000\n                                ","m-TMSI":"\n                                    11000010000110101011010100111111\n                                "}},"cn-Domain":{"ps":null}}}}}}},"hex":"3C6D6573736167652D626F64"},{"time":"1344738843","channel":"DL-DCCH-Message","event":"csfbParametersResponseCDMA2000","DL-DCCH-Message":{"message":{"c1":{"csfbParametersResponseCDMA2000":{"rrc-TransactionIdentifier":"0","criticalExtensions":{"criticalExtensionsFuture":""}}}}},"hex":"3C6D6573736167"},{"time":"1501099455","channel":"PCCH-Message","event":"paging","PCCH-Message":{"message":{"c1":{"paging":{"pagingRecordList":{"PagingRecord":{"ue-Identity":{"s-TMSI":{"mmec":"\n                                    00111000\n                                ","m-TMSI":"\n                                    11000010000110100001000100110000\n                                "}},"cn-Domain":{"ps":null}}}}}}},"hex":"3C6D6573736167652D626F64"},{"time":"1501099455","channel":"PCCH-Message","event":"paging","PCCH-Message":{"message":{"c1":{"paging":{"pagingRecordList":{"PagingRecord":[{"ue-Identity":{"s-TMSI":{"mmec":"\n                                    00111000\n                                ","m-TMSI":"\n                                    11010010000111000111110110100010\n                                "}},"cn-Domain":{"ps":null}},{"ue-Identity":{"s-TMSI":{"mmec":"\n                                    00111000\n                                ","m-TMSI":"\n                                    11010010000000000011011111010011\n                                "}},"cn-Domain":{"ps":null}},{"ue-Identity":{"s-TMSI":{"mmec":"\n                                    00111000\n                                ","m-TMSI":"\n                                    11100010000101010000001001010100\n                                "}},"cn-Domain":{"ps":null}}]}}}}},"hex":"3C6D6573736167652D626F64793E3C74696D653E31353031303939"},{"time":"1501099457","channel":"PCCH-Message","event":"paging","PCCH-Message":{"message":{"c1":{"paging":{"pagingRecordList":{"PagingRecord":[{"ue-Identity":{"s-TMSI":{"mmec":"\n                                    00111000\n                                ","m-TMSI":"\n                                    11000010000111010010010101100101\n                                "}},"cn-Domain":{"ps":null}},{"ue-Identity":{"s-TMSI":{"mmec":"\n                                    00111000\n                                ","m-TMSI":"\n                                    11010010000100101010001111111101\n                                "}},"cn-Domain":{"ps":null}}]}}}}},"hex":"3C6D6573736167652D626F64793E3C74696D65"},{"time":"1344739745","channel":"DL-DCCH-Message","event":"messageClassExtension","DL-DCCH-Message":{"message":{"messageClassExtension":""}},"hex":"3C6D65"},{"time":"1501099458","channel":"PCCH-Message","event":"paging","PCCH-Message":{"message":{"c1":{"paging":{"pagingRecordList":{"PagingRecord":{"ue-Identity":{"s-TMSI":{"mmec":"\n                                    00111000\n                                ","m-TMSI":"\n                                    11000010000000000011100001001001\n                                "}},"cn-Domain":{"ps":null}}}}}}},"hex":"3C6D6573736167652D626F64"},{"time":"1501099458","channel":"PCCH-Message","event":"paging","PCCH-Message":{"message":{"c1":{"paging":{"pagingRecordList":{"PagingRecord":{"ue-Identity":{"s-TMSI":{"mmec":"\n                                    00111000\n                                ","m-TMSI":"\n                                    11000010000000000011100001001001\n                                "}},"cn-Domain":{"ps":null}}}}}}},"hex":"3C6D6573736167652D626F64"},{"time":"1501099458","channel":"PCCH-Message","event":"paging","PCCH-Message":{"message":{"c1":{"paging":{"pagingRecordList":{"PagingRecord":{"ue-Identity":{"s-TMSI":{"mmec":"\n                                    00111000\n                                ","m-TMSI":"\n                                    11000010000101111101010111010000\n                                "}},"cn-Domain":{"cs":null}}}}}}},"hex":"3C6D6573736167652D626F64"},{"time":"1344739990","channel":"DL-DCCH-Message","event":"csfbParametersResponseCDMA2000","DL-DCCH-Message":{"message":{"c1":{"csfbParametersResponseCDMA2000":{"rrc-TransactionIdentifier":"0","criticalExtensions":{"criticalExtensionsFuture":""}}}}},"hex":"3C6D6573736167"},{"time":"1501099460","channel":"PCCH-Message","event":"paging","PCCH-Message":{"message":{"c1":{"paging":{"pagingRecordList":{"PagingRecord":{"ue-Identity":{"s-TMSI":{"mmec":"\n                                    00111000\n                                ","m-TMSI":"\n                                    11011011000101101011010001001110\n                                "}},"cn-Domain":{"ps":null}}}}}}},"hex":"3C6D6573736167652D626F64"},{"time":"1501099460","channel":"PCCH-Message","event":"paging","PCCH-Message":{"message":{"c1":{"paging":{"pagingRecordList":{"PagingRecord":{"ue-Identity":{"s-TMSI":{"mmec":"\n                                    00111000\n                                ","m-TMSI":"\n                                    11011011000101101011010001001110\n                                "}},"cn-Domain":{"ps":null}}}}}}},"hex":"3C6D6573736167652D626F64"},{"time":"1501099461","channel":"PCCH-Message","event":"paging","PCCH-Message":{"message":{"c1":{"paging":{"pagingRecordList":{"PagingRecord":{"ue-Identity":{"s-TMSI":{"mmec":"\n                                    00111000\n                                ","m-TMSI":"\n                                    11011011000101101011010001001110\n                                "}},"cn-Domain":{"ps":null}}}}}}},"hex":"3C6D6573736167652D626F64"},{"time":"1501099461","channel":"PCCH-Message","event":"paging","PCCH-Message":{"message":{"c1":{"paging":{"pagingRecordList":{"PagingRecord":[{"ue-Identity":{"s-TMSI":{"mmec":"\n                                    00111000\n                                ","m-TMSI":"\n                                    11001110000110001110110111111110\n                                "}},"cn-Domain":{"ps":null}},{"ue-Identity":{"s-TMSI":{"mmec":"\n                                    00111000\n                                ","m-TMSI":"\n                                    11100010000001111011011001000100\n                                "}},"cn-Domain":{"ps":null}}]}}}}},"hex":"3C6D6573736167652D626F64793E3C74696D65"},{"time":"1501099463","channel":"PCCH-Message","event":"paging","PCCH-Message":{"message":{"c1":{"paging":{"pagingRecordList":{"PagingRecord":{"ue-Identity":{"s-TMSI":{"mmec":"\n                                    00111000\n                                ","m-TMSI":"\n                                    11000111000000010101110100011011\n                                "}},"cn-Domain":{"ps":null}}}}}}},"hex":"3C6D6573736167652D626F64"},{"time":"1501099463","channel":"PCCH-Message","event":"paging","PCCH-Message":{"message":{"c1":{"paging":{"pagingRecordList":{"PagingRecord":{"ue-Identity":{"s-TMSI":{"mmec":"\n                                    00111000\n                                ","m-TMSI":"\n                                    11000111000000010101110100011011\n                                "}},"cn-Domain":{"ps":null}}}}}}},"hex":"3C6D6573736167652D626F64"},{"time":"1501099464","channel":"PCCH-Message","event":"paging","PCCH-Message":{"message":{"c1":{"paging":{"pagingRecordList":{"PagingRecord":{"ue-Identity":{"s-TMSI":{"mmec":"\n                                    00111000\n                                ","m-TMSI":"\n                                    11000111000000010101110100011011\n                                "}},"cn-Domain":{"ps":null}}}}}}},"hex":"3C6D6573736167652D626F64"},{"time":"1501099464","channel":"DL-CCCH-Message","event":"messageClassExtension","DL-CCCH-Message":{"message":{"messageClassExtension":""}},"hex":"3C6D65"},{"time":"1501099465","channel":"PCCH-Message","event":"paging","PCCH-Message":{"message":{"c1":{"paging":{"pagingRecordList":{"PagingRecord":{"ue-Identity":{"s-TMSI":{"mmec":"\n                                    00111000\n                                ","m-TMSI":"\n                                    11101011000100100111100111100010\n                                "}},"cn-Domain":{"ps":null}}}}}}},"hex":"3C6D6573736167652D626F64"},{"time":"1501099466","channel":"PCCH-Message","event":"paging","PCCH-Message":{"message":{"c1":{"paging":{"pagingRecordList":{"PagingRecord":{"ue-Identity":{"s-TMSI":{"mmec":"\n                                    00111000\n                                ","m-TMSI":"\n                                    11101011000100100111100111100010\n                                "}},"cn-Domain":{"ps":null}}}}}}},"hex":"3C6D6573736167652D626F64"},{"time":"1501099466","channel":"PCCH-Message","event":"paging","PCCH-Message":{"message":{"c1":{"paging":{"pagingRecordList":{"PagingRecord":{"ue-Identity":{"s-TMSI":{"mmec":"\n                                    00111000\n                                ","m-TMSI":"\n                                    11101011000100100111100111100010\n                                "}},"cn-Domain":{"ps":null}}}}}}},"hex":"3C6D6573736167652D626F64"},{"time":"1501099467","channel":"PCCH-Message","event":"paging","PCCH-Message":{"message":{"c1":{"paging":{"pagingRecordList":{"PagingRecord":{"ue-Identity":{"s-TMSI":{"mmec":"\n                                    00111000\n                                ","m-TMSI":"\n                                    11101011000100100111100111100010\n                                "}},"cn-Domain":{"ps":null}}}}}}},"hex":"3C6D6573736167652D626F64"},{"time":"1501099467","channel":"PCCH-Message","event":"paging","PCCH-Message":{"message":{"c1":{"paging":{"pagingRecordList":{"PagingRecord":[{"ue-Identity":{"s-TMSI":{"mmec":"\n                                    00111000\n                                ","m-TMSI":"\n                                    11100010000101010000001001010100\n                                "}},"cn-Domain":{"ps":null}},{"ue-Identity":{"s-TMSI":{"mmec":"\n                                    00111000\n                                ","m-TMSI":"\n                                    11100010000101111101000101000001\n                                "}},"cn-Domain":{"ps":null}}]}}}}},"hex":"3C6D6573736167652D626F64793E3C74696D65"},{"time":"1501099467","channel":"PCCH-Message","event":"paging","PCCH-Message":{"message":{"c1":{"paging":{"pagingRecordList":{"PagingRecord":[{"ue-Identity":{"s-TMSI":{"mmec":"\n                                    00111000\n                                ","m-TMSI":"\n                                    11100010000101010000001001010100\n                                "}},"cn-Domain":{"ps":null}},{"ue-Identity":{"s-TMSI":{"mmec":"\n                                    00111000\n                                ","m-TMSI":"\n                                    11100010000101111101000101000001\n                                "}},"cn-Domain":{"ps":null}}]}}}}},"hex":"3C6D6573736167652D626F64793E3C74696D65"},{"time":"1501099468","channel":"PCCH-Message","event":"paging","PCCH-Message":{"message":{"c1":{"paging":{"pagingRecordList":{"PagingRecord":[{"ue-Identity":{"s-TMSI":{"mmec":"\n                                    00111000\n                                ","m-TMSI":"\n                                    11100010000101010000001001010100\n                                "}},"cn-Domain":{"ps":null}},{"ue-Identity":{"s-TMSI":{"mmec":"\n                                    00111000\n                                ","m-TMSI":"\n                                    11100010000101111101000101000001\n                                "}},"cn-Domain":{"ps":null}}]}}}}},"hex":"3C6D6573736167652D626F64793E3C74696D65"},{"time":"1501099468","channel":"PCCH-Message","event":"paging","PCCH-Message":{"message":{"c1":{"paging":{"pagingRecordList":{"PagingRecord":{"ue-Identity":{"s-TMSI":{"mmec":"\n                                    00111000\n                                ","m-TMSI":"\n                                    11000010000001011011101001110101\n                                "}},"cn-Domain":{"ps":null}}}}}}},"hex":"3C6D6573736167652D626F64"},{"time":"1501099469","channel":"PCCH-Message","event":"paging","PCCH-Message":{"message":{"c1":{"paging":{"pagingRecordList":{"PagingRecord":{"ue-Identity":{"s-TMSI":{"mmec":"\n                                    00111000\n                                ","m-TMSI":"\n                                    11000010000001011011101001110101\n                                "}},"cn-Domain":{"ps":null}}}}}}},"hex":"3C6D6573736167652D626F64"},{"time":"1501099469","channel":"PCCH-Message","event":"paging","PCCH-Message":{"message":{"c1":{"paging":{"pagingRecordList":{"PagingRecord":{"ue-Identity":{"s-TMSI":{"mmec":"\n                                    00111000\n                                ","m-TMSI":"\n                                    11000010000001011011101001110101\n                                "}},"cn-Domain":{"ps":null}}}}}}},"hex":"3C6D6573736167652D626F64"},{"time":"1344742695","channel":"DL-DCCH-Message","event":"loggedMeasurementConfiguration-r10","DL-DCCH-Message":{"message":{"c1":{"loggedMeasurementConfiguration-r10":{"criticalExtensions":{"criticalExtensionsFuture":""}}}}},"hex":"3C6D65737361"},{"time":"1501099470","channel":"PCCH-Message","event":"paging","PCCH-Message":{"message":{"c1":{"paging":{"pagingRecordList":{"PagingRecord":{"ue-Identity":{"s-TMSI":{"mmec":"\n                                    00111000\n                                ","m-TMSI":"\n                                    11100110000000100011111000001111\n                                "}},"cn-Domain":{"ps":null}}}}}}},"hex":"3C6D6573736167652D626F64"},{"time":"1501099470","channel":"DL-CCCH-Message","event":"messageClassExtension","DL-CCCH-Message":{"message":{"messageClassExtension":""}},"hex":"3C6D65"},{"time":"1501099471","channel":"PCCH-Message","event":"paging","PCCH-Message":{"message":{"c1":{"paging":{"pagingRecordList":{"PagingRecord":{"ue-Identity":{"s-TMSI":{"mmec":"\n                                    00111000\n                                ","m-TMSI":"\n                                    11000010000001000101010101110111\n                                "}},"cn-Domain":{"ps":null}}}}}}},"hex":"3C6D6573736167652D626F64"},{"time":"1501099471","channel":"PCCH-Message","event":"paging","PCCH-Message":{"message":{"c1":{"paging":{"pagingRecordList":{"PagingRecord":[{"ue-Identity":{"s-TMSI":{"mmec":"\n                                    00111000\n                                ","m-TMSI":"\n                                    11100010000011101001010001111000\n                                "}},"cn-Domain":{"ps":null}},{"ue-Identity":{"s-TMSI":{"mmec":"\n                                    00111000\n                                ","m-TMSI":"\n                                    11100010000001000011001111010111\n                                "}},"cn-Domain":{"ps":null}},{"ue-Identity":{"s-TMSI":{"mmec":"\n                                    00111000\n                                ","m-TMSI":"\n                                    11100001000011100111000011110110\n                                "}},"cn-Domain":{"ps":null}},{"ue-Identity":{"s-TMSI":{"mmec":"\n                                    00111000\n                                ","m-TMSI":"\n                                    11111000000001111000110000011010\n                                "}},"cn-Domain":{"ps":null}}]}}}}},"hex":"3C6D6573736167652D626F64793E3C74696D653E313530313039393437313C2F74696D"},{"time":"1501099472","channel":"PCCH-Message","event":"paging","PCCH-Message":{"message":{"c1":{"paging":{"pagingRecordList":{"PagingRecord":{"ue-Identity":{"s-TMSI":{"mmec":"\n                                    00111000\n                                ","m-TMSI":"\n                                    11110110000001111111011010001001\n                                "}},"cn-Domain":{"ps":null}}}}}}},"hex":"3C6D6573736167652D626F64"},{"time":"1501099472","channel":"DL-DCCH-Message","event":"csfbParametersResponseCDMA2000","DL-DCCH-Message":{"message":{"c1":{"csfbParametersResponseCDMA2000":{"rrc-TransactionIdentifier":"0","criticalExtensions":{"csfbParametersResponseCDMA2000-r8":{"rand":"\n                            00000000000000000000111010000000\n                        ","mobilityParameters":"1E C0 FE D1 20 6F EC"}}}}}},"hex":"3C6D6573736167652D626F"},{"time":"1501099472","channel":"UL-DCCH-Message","event":"csfbParametersRequestCDMA20000","UL-DCCH-Message":{"message":{"c1":{"csfbParametersRequestCDMA2000":{"criticalExtensions":{"csfbParametersRequestCDMA2000-r8":""}}}}},"hex":"3C6D65737361"},{"time":"1501099473","channel":"PCCH-Message~","event":"messageClassExtension","PCCH-Message":{"message":{"messageClassExtension":""}},"hex":"3C6D65"},{"time":"1501099473","channel":"UL-DCCH-Messagetension","event":"ulHandoverPreparationTransfer","UL-DCCH-Message":{"message":{"c1":{"ulHandoverPreparationTransfer":{"criticalExtensions":{"c1":{"spare3":""}}}}}},"hex":"3C6D65737361"},{"time":"1501099473","channel":"PCCH-Message","event":"paging","PCCH-Message":{"message":{"c1":{"paging":{"pagingRecordList":{"PagingRecord":{"ue-Identity":{"s-TMSI":{"mmec":"\n                                    00111000\n                                ","m-TMSI":"\n                                    11100010000001111011011001000100\n                                "}},"cn-Domain":{"ps":null}}}}}}},"hex":"3C6D6573736167652D626F64"},{"time":"1501099474","channel":"PCCH-Message","event":"paging","PCCH-Message":{"message":{"c1":{"paging":{"pagingRecordList":{"PagingRecord":[{"ue-Identity":{"s-TMSI":{"mmec":"\n                                    00111000\n                                ","m-TMSI":"\n                                    11100100000001111001110001000110\n                                "}},"cn-Domain":{"ps":null}},{"ue-Identity":{"s-TMSI":{"mmec":"\n                                    00111000\n                                ","m-TMSI":"\n                                    11100010000101010000001001010100\n                                "}},"cn-Domain":{"ps":null}}]}}}}},"hex":"3C6D6573736167652D626F64793E3C74696D65"},{"time":"1501099474","channel":"PCCH-Message","event":"paging","PCCH-Message":{"message":{"c1":{"paging":{"pagingRecordList":{"PagingRecord":{"ue-Identity":{"s-TMSI":{"mmec":"\n                                    00111000\n                                ","m-TMSI":"\n                                    11001110000111100111000011111000\n                                "}},"cn-Domain":{"ps":null}}}}}}},"hex":"3C6D6573736167652D626F64"},{"time":"1344744004","channel":"DL-DCCH-Message","event":"handoverFromEUTRAPreparationRequest","DL-DCCH-Message":{"message":{"c1":{"handoverFromEUTRAPreparationRequest":{"rrc-TransactionIdentifier":"2","criticalExtensions":{"c1":{"spare1":""}}}}}},"hex":"3C6D6573736167"},{"time":"1501099474","channel":"UL-CCCH-Message","event":"rrcConnectionRequest","UL-CCCH-Message":{"message":{"c1":{"rrcConnectionRequest":{"criticalExtensions":{"rrcConnectionRequest-r8":{"ue-Identity":{"s-TMSI":{"mmec":"\n                                    00011000\n                                ","m-TMSI":"\n                                    10010000000100000000000000000000\n                                "}},"establishmentCause":{"emergency":null},"spare":"\n                            0\n                        "}}}}}},"hex":"3C6D6573736167652D626F64793E"},{"time":"1501099475","channel":"PCCH-Message","event":"paging","PCCH-Message":{"message":{"c1":{"paging":{"pagingRecordList":{"PagingRecord":{"ue-Identity":{"s-TMSI":{"mmec":"\n                                    00111000\n                                ","m-TMSI":"\n                                    11010010000000000011011111010101\n                                "}},"cn-Domain":{"cs":null}}}}}}},"hex":"3C6D6573736167652D626F64"},{"time":"1501099476","channel":"PCCH-Message","event":"paging","PCCH-Message":{"message":{"c1":{"paging":{"pagingRecordList":{"PagingRecord":{"ue-Identity":{"s-TMSI":{"mmec":"\n                                    00111000\n                                ","m-TMSI":"\n                                    11000010000100100100010011010011\n                                "}},"cn-Domain":{"ps":null}}}}}}},"hex":"3C6D6573736167652D626F64"},{"time":"1501099477","channel":"PCCH-Message","event":"paging","PCCH-Message":{"message":{"c1":{"paging":{"pagingRecordList":{"PagingRecord":{"ue-Identity":{"s-TMSI":{"mmec":"\n                                    00111000\n                                ","m-TMSI":"\n                                    11100010000100101001011111111100\n                                "}},"cn-Domain":{"ps":null}}}}}}},"hex":"3C6D6573736167652D626F64"},{"time":"1501099477","channel":"PCCH-Message","event":"paging","PCCH-Message":{"message":{"c1":{"paging":{"pagingRecordList":{"PagingRecord":{"ue-Identity":{"s-TMSI":{"mmec":"\n                                    00111000\n                                ","m-TMSI":"\n                                    11100010000100101001011111111100\n                                "}},"cn-Domain":{"ps":null}}}}}}},"hex":"3C6D6573736167652D626F64"},{"time":"1501099477","channel":"PCCH-Message","event":"paging","PCCH-Message":{"message":{"c1":{"paging":{"pagingRecordList":{"PagingRecord":{"ue-Identity":{"s-TMSI":{"mmec":"\n                                    00111000\n                                ","m-TMSI":"\n                                    11100010000100101001011111111100\n                                "}},"cn-Domain":{"ps":null}}}}}}},"hex":"3C6D6573736167652D626F64"},{"time":"1501099478","channel":"PCCH-Message","event":"paging","PCCH-Message":{"message":{"c1":{"paging":{"pagingRecordList":{"PagingRecord":{"ue-Identity":{"s-TMSI":{"mmec":"\n                                    00111000\n                                ","m-TMSI":"\n                                    11100010000100101001011111111100\n                                "}},"cn-Domain":{"ps":null}}}}}}},"hex":"3C6D6573736167652D626F64"},{"time":"1501099478","channel":"PCCH-Message","event":"paging","PCCH-Message":{"message":{"c1":{"paging":{"pagingRecordList":{"PagingRecord":[{"ue-Identity":{"s-TMSI":{"mmec":"\n                                    10010000\n                                ","m-TMSI":"\n                                    00010000000000000000000000000000\n                                "}},"cn-Domain":{"ps":null}},{"ue-Identity":{"s-TMSI":{"mmec":"\n                                    00000000\n                                ","m-TMSI":"\n                                    00000000000000000001000000100111\n                                "}},"cn-Domain":{"ps":null}},{"ue-Identity":{"imsi":{"IMSI-Digit":["15","15","0","0","15","15","15","15","15","15","15","15","3","1","1"]}},"cn-Domain":{"cs":null}},{"ue-Identity":{"imsi":{"IMSI-Digit":["5","0","7","0","1","5","1","8","9","0","1","7","5","4","12","0"]}},"cn-Domain":{"ps":null}}]}}}}},"hex":"3C6D6573736167652D626F64793E3C74696D653E313530313039393437383C2F74696D653E3C6368616E6E656C3E504343482D4D6573"},{"time":"1501099479","channel":"PCCH-Message","event":"paging","PCCH-Message":{"message":{"c1":{"paging":{"pagingRecordList":{"PagingRecord":{"ue-Identity":{"s-TMSI":{"mmec":"\n                                    00111000\n                                ","m-TMSI":"\n                                    11100010000001111011011001000100\n                                "}},"cn-Domain":{"ps":null}}}}}}},"hex":"3C6D6573736167652D626F64"},{"time":"1501099480","channel":"PCCH-Message","event":"paging","PCCH-Message":{"message":{"c1":{"paging":{"pagingRecordList":{"PagingRecord":[{"ue-Identity":{"s-TMSI":{"mmec":"\n                                    00111000\n                                ","m-TMSI":"\n                                    11000010000111010011000111000110\n                                "}},"cn-Domain":{"ps":null}},{"ue-Identity":{"s-TMSI":{"mmec":"\n                                    00111000\n                                ","m-TMSI":"\n                                    11000001000001100000000101100000\n                                "}},"cn-Domain":{"ps":null}}]}}}}},"hex":"3C6D6573736167652D626F64793E3C74696D65"},{"time":"1501099480","channel":"PCCH-Message","event":"paging","PCCH-Message":{"message":{"c1":{"paging":{"pagingRecordList":{"PagingRecord":{"ue-Identity":{"s-TMSI":{"mmec":"\n                                    00111000\n                                ","m-TMSI":"\n                                    11100010000101010000001001010100\n                                "}},"cn-Domain":{"ps":null}}}}}}},"hex":"3C6D6573736167652D626F64"},{"time":"1501099480","channel":"PCCH-Message","event":"paging","PCCH-Message":{"message":{"c1":{"paging":{"pagingRecordList":{"PagingRecord":{"ue-Identity":{"s-TMSI":{"mmec":"\n                                    00111000\n                                ","m-TMSI":"\n                                    11100010000101010000001001010100\n                                "}},"cn-Domain":{"ps":null}}}}}}},"hex":"3C6D6573736167652D626F64"},{"time":"1501099481","channel":"PCCH-Message","event":"paging","PCCH-Message":{"message":{"c1":{"paging":{"pagingRecordList":{"PagingRecord":{"ue-Identity":{"s-TMSI":{"mmec":"\n                                    00111000\n                                ","m-TMSI":"\n                                    11100010000101010000001001010100\n                                "}},"cn-Domain":{"ps":null}}}}}}},"hex":"3C6D6573736167652D626F64"},{"time":"1501099483","channel":"PCCH-Message","event":"paging","PCCH-Message":{"message":{"c1":{"paging":{"pagingRecordList":{"PagingRecord":{"ue-Identity":{"s-TMSI":{"mmec":"\n                                    00111000\n                                ","m-TMSI":"\n                                    11100010000101010000001001010100\n                                "}},"cn-Domain":{"ps":null}}}}}}},"hex":"3C6D6573736167652D626F64"},{"time":"1501099484","channel":"PCCH-Message","event":"paging","PCCH-Message":{"message":{"c1":{"paging":{"pagingRecordList":{"PagingRecord":{"ue-Identity":{"s-TMSI":{"mmec":"\n                                    00111000\n                                ","m-TMSI":"\n                                    11100010000101010000001001010100\n                                "}},"cn-Domain":{"ps":null}}}}}}},"hex":"3C6D6573736167652D626F64"},{"time":"1501099486","channel":"PCCH-Message","event":"paging","PCCH-Message":{"message":{"c1":{"paging":{"pagingRecordList":{"PagingRecord":{"ue-Identity":{"s-TMSI":{"mmec":"\n                                    00111000\n                                ","m-TMSI":"\n                                    11100010000101010000001001010100\n                                "}},"cn-Domain":{"ps":null}}}}}}},"hex":"3C6D6573736167652D626F64"},{"time":"1501099486","channel":"PCCH-Message","event":"paging","PCCH-Message":{"message":{"c1":{"paging":{"pagingRecordList":{"PagingRecord":{"ue-Identity":{"s-TMSI":{"mmec":"\n                                    00111000\n                                ","m-TMSI":"\n                                    11100010000101010000001001010100\n                                "}},"cn-Domain":{"ps":null}}}}}}},"hex":"3C6D6573736167652D626F64"},{"time":"1501099487","channel":"PCCH-Message","event":"paging","PCCH-Message":{"message":{"c1":{"paging":{"pagingRecordList":{"PagingRecord":{"ue-Identity":{"s-TMSI":{"mmec":"\n                                    00111000\n                                ","m-TMSI":"\n                                    11100010000101010000001001010100\n                                "}},"cn-Domain":{"ps":null}}}}}}},"hex":"3C6D6573736167652D626F64"},{"time":"1501099488","channel":"PCCH-Message","event":"paging","PCCH-Message":{"message":{"c1":{"paging":{"pagingRecordList":{"PagingRecord":[{"ue-Identity":{"s-TMSI":{"mmec":"\n                                    00111000\n                                ","m-TMSI":"\n                                    11000010000110100111110011001001\n                                "}},"cn-Domain":{"ps":null}},{"ue-Identity":{"s-TMSI":{"mmec":"\n                                    00111000\n                                ","m-TMSI":"\n                                    11110110000001100011100010000000\n                                "}},"cn-Domain":{"ps":null}}]}}}}},"hex":"3C6D6573736167652D626F64793E3C74696D65"},{"time":"1501099489","channel":"PCCH-Message","event":"paging","PCCH-Message":{"message":{"c1":{"paging":{"pagingRecordList":{"PagingRecord":{"ue-Identity":{"s-TMSI":{"mmec":"\n                                    00111000\n                                ","m-TMSI":"\n                                    11110010000001111000011000100010\n                                "}},"cn-Domain":{"ps":null}}}}}}},"hex":"3C6D6573736167652D626F64"},{"time":"1501099492","channel":"PCCH-Message","event":"paging","PCCH-Message":{"message":{"c1":{"paging":{"pagingRecordList":{"PagingRecord":[{"ue-Identity":{"s-TMSI":{"mmec":"\n                                    00111000\n                                ","m-TMSI":"\n                                    11010010000001011101010101110001\n                                "}},"cn-Domain":{"ps":null}},{"ue-Identity":{"s-TMSI":{"mmec":"\n                                    00111000\n                                ","m-TMSI":"\n                                    11100001000101010111101001000011\n                                "}},"cn-Domain":{"ps":null}},{"ue-Identity":{"s-TMSI":{"mmec":"\n                                    00111000\n                                ","m-TMSI":"\n                                    11100010000101010000001001010100\n                                "}},"cn-Domain":{"ps":null}},{"ue-Identity":{"s-TMSI":{"mmec":"\n                                    00111000\n                                ","m-TMSI":"\n                                    11000010000101000100010011010011\n                                "}},"cn-Domain":{"ps":null}}]}}}}},"hex":"3C6D6573736167652D626F64793E3C74696D653E313530313039393439323C2F74696D"},{"time":"1344748593","channel":"DL-DCCH-Message","event":"messageClassExtension","DL-DCCH-Message":{"message":{"messageClassExtension":""}},"hex":"3C6D65"},{"time":"1501099494","channel":"PCCH-Message","event":"paging","PCCH-Message":{"message":{"c1":{"paging":{"pagingRecordList":{"PagingRecord":{"ue-Identity":{"s-TMSI":{"mmec":"\n                                    00111000\n                                ","m-TMSI":"\n                                    11010010000000000011011111010101\n                                "}},"cn-Domain":{"cs":null}}}}}}},"hex":"3C6D6573736167652D626F64"},{"time":"1501099494","channel":"PCCH-Message","event":"paging","PCCH-Message":{"message":{"c1":{"paging":{"pagingRecordList":{"PagingRecord":[{"ue-Identity":{"s-TMSI":{"mmec":"\n                                    00111000\n                                ","m-TMSI":"\n                                    11100010000001111011011001000100\n                                "}},"cn-Domain":{"ps":null}},{"ue-Identity":{"s-TMSI":{"mmec":"\n                                    00111000\n                                ","m-TMSI":"\n                                    11110010000000000010111010100001\n                                "}},"cn-Domain":{"ps":null}},{"ue-Identity":{"s-TMSI":{"mmec":"\n                                    00111000\n                                ","m-TMSI":"\n                                    11010010000000011001100011111000\n                                "}},"cn-Domain":{"ps":null}},{"ue-Identity":{"s-TMSI":{"mmec":"\n                                    00111000\n                                ","m-TMSI":"\n                                    11110101000011011000100110100001\n                                "}},"cn-Domain":{"ps":null}}]}}}}},"hex":"3C6D6573736167652D626F64793E3C74696D653E313530313039393439343C2F74696D"},{"time":"1501099495","channel":"PCCH-Message","event":"paging","PCCH-Message":{"message":{"c1":{"paging":{"pagingRecordList":{"PagingRecord":{"ue-Identity":{"s-TMSI":{"mmec":"\n                                    00111000\n                                ","m-TMSI":"\n                                    11000011000000111001100001011100\n                                "}},"cn-Domain":{"ps":null}}}}}}},"hex":"3C6D6573736167652D626F64"},{"time":"1501099496","channel":"PCCH-Message","event":"paging","PCCH-Message":{"message":{"c1":{"paging":{"pagingRecordList":{"PagingRecord":{"ue-Identity":{"s-TMSI":{"mmec":"\n                                    00111000\n                                ","m-TMSI":"\n                                    11000011000000111001100001011100\n                                "}},"cn-Domain":{"ps":null}}}}}}},"hex":"3C6D6573736167652D626F64"},{"time":"1501099497","channel":"PCCH-Message","event":"paging","PCCH-Message":{"message":{"c1":{"paging":{"pagingRecordList":{"PagingRecord":{"ue-Identity":{"s-TMSI":{"mmec":"\n                                    00111000\n                                ","m-TMSI":"\n                                    11011101000010101011100110110101\n                                "}},"cn-Domain":{"ps":null}}}}}}},"hex":"3C6D6573736167652D626F64"},{"time":"1501099499","channel":"PCCH-Message","event":"paging","PCCH-Message":{"message":{"c1":{"paging":{"pagingRecordList":{"PagingRecord":{"ue-Identity":{"s-TMSI":{"mmec":"\n                                    00111000\n                                ","m-TMSI":"\n                                    11011101000010101011100110110101\n                                "}},"cn-Domain":{"ps":null}}}}}}},"hex":"3C6D6573736167652D626F64"},{"time":"1501099499","channel":"PCCH-Message","event":"paging","PCCH-Message":{"message":{"c1":{"paging":{"pagingRecordList":{"PagingRecord":[{"ue-Identity":{"s-TMSI":{"mmec":"\n                                    00111000\n                                ","m-TMSI":"\n                                    11101010000010001101000110101011\n                                "}},"cn-Domain":{"ps":null}},{"ue-Identity":{"s-TMSI":{"mmec":"\n                                    00111000\n                                ","m-TMSI":"\n                                    11100010000101010000001001010100\n                                "}},"cn-Domain":{"ps":null}},{"ue-Identity":{"s-TMSI":{"mmec":"\n                                    00111000\n                                ","m-TMSI":"\n                                    11100010000101100111110100010110\n                                "}},"cn-Domain":{"ps":null}}]}}}}},"hex":"3C6D6573736167652D626F64793E3C74696D653E31353031303939"},{"time":"1501099500","channel":"PCCH-Message","event":"paging","PCCH-Message":{"message":{"c1":{"paging":{"pagingRecordList":{"PagingRecord":{"ue-Identity":{"s-TMSI":{"mmec":"\n                                    00111000\n                                ","m-TMSI":"\n                                    11100010000001111011011001000100\n                                "}},"cn-Domain":{"ps":null}}}}}}},"hex":"3C6D6573736167652D626F64"},{"time":"1501099500","channel":"PCCH-Message","event":"paging","PCCH-Message":{"message":{"c1":{"paging":{"pagingRecordList":{"PagingRecord":{"ue-Identity":{"s-TMSI":{"mmec":"\n                                    00111000\n                                ","m-TMSI":"\n                                    11100010000001111011011001000100\n                                "}},"cn-Domain":{"ps":null}}}}}}},"hex":"3C6D6573736167652D626F64"},{"time":"1501099501","channel":"PCCH-Message","event":"paging","PCCH-Message":{"message":{"c1":{"paging":{"pagingRecordList":{"PagingRecord":{"ue-Identity":{"s-TMSI":{"mmec":"\n                                    00111000\n                                ","m-TMSI":"\n                                    11100010000001111011011001000100\n                                "}},"cn-Domain":{"ps":null}}}}}}},"hex":"3C6D6573736167652D626F64"},{"time":"1501099503","channel":"PCCH-Message","event":"paging","PCCH-Message":{"message":{"c1":{"paging":{"pagingRecordList":{"PagingRecord":{"ue-Identity":{"s-TMSI":{"mmec":"\n                                    00111000\n                                ","m-TMSI":"\n                                    11100010000001111011011001000100\n                                "}},"cn-Domain":{"ps":null}}}}}}},"hex":"3C6D6573736167652D626F64"},{"time":"1501099503","channel":"UL-DCCH-Message","event":"csfbParametersRequestCDMA2000","UL-DCCH-Message":{"message":{"c1":{"csfbParametersRequestCDMA2000":{"criticalExtensions":{"csfbParametersRequestCDMA2000-r8":""}}}}},"hex":"3C6D65737361"},{"time":"1501099504","channel":"PCCH-Message~","event":"paging","PCCH-Message":{"message":{"c1":{"paging":{"pagingRecordList":{"PagingRecord":{"ue-Identity":{"s-TMSI":{"mmec":"\n                                    00111000\n                                ","m-TMSI":"\n                                    11010011000011010100000001010010\n                                "}},"cn-Domain":{"ps":null}}}}}}},"hex":"3C6D6573736167652D626F64"},{"time":"1344751542","channel":"DL-DCCH-Message","event":"csfbParametersResponseCDMA2000","DL-DCCH-Message":{"message":{"c1":{"csfbParametersResponseCDMA2000":{"rrc-TransactionIdentifier":"0","criticalExtensions":{"criticalExtensionsFuture":""}}}}},"hex":"3C6D6573736167"},{"time":"1501099504","channel":"PCCH-Message","event":"paging","PCCH-Message":{"message":{"c1":{"paging":{"pagingRecordList":{"PagingRecord":{"ue-Identity":{"s-TMSI":{"mmec":"\n                                    00111000\n                                ","m-TMSI":"\n                                    11010011000111000111011111001010\n                                "}},"cn-Domain":{"ps":null}}}}}}},"hex":"3C6D6573736167652D626F64"},{"time":"1501099504","channel":"PCCH-Message","event":"paging","PCCH-Message":{"message":{"c1":{"paging":{"pagingRecordList":{"PagingRecord":{"ue-Identity":{"s-TMSI":{"mmec":"\n                                    00111000\n                                ","m-TMSI":"\n                                    11010011000111000111011111001010\n                                "}},"cn-Domain":{"ps":null}}}}}}},"hex":"3C6D6573736167652D626F64"},{"time":"1501099505","channel":"PCCH-Message","event":"paging","PCCH-Message":{"message":{"c1":{"paging":{"pagingRecordList":{"PagingRecord":[{"ue-Identity":{"s-TMSI":{"mmec":"\n                                    00111000\n                                ","m-TMSI":"\n                                    11100010000101010000001001010100\n                                "}},"cn-Domain":{"ps":null}},{"ue-Identity":{"s-TMSI":{"mmec":"\n                                    00111000\n                                ","m-TMSI":"\n                                    11011010000011000100110011101100\n                                "}},"cn-Domain":{"ps":null}}]}}}}},"hex":"3C6D6573736167652D626F64793E3C74696D65"},{"time":"1501099506","channel":"PCCH-Message","event":"paging","PCCH-Message":{"message":{"c1":{"paging":{"pagingRecordList":{"PagingRecord":{"ue-Identity":{"s-TMSI":{"mmec":"\n                                    00111000\n                                ","m-TMSI":"\n                                    11001011000111001010101100011111\n                                "}},"cn-Domain":{"ps":null}}}}}}},"hex":"3C6D6573736167652D626F64"},{"time":"1501099506","channel":"PCCH-Message","event":"paging","PCCH-Message":{"message":{"c1":{"paging":{"pagingRecordList":{"PagingRecord":{"ue-Identity":{"s-TMSI":{"mmec":"\n                                    00111000\n                                ","m-TMSI":"\n                                    11001011000111001010101100011111\n                                "}},"cn-Domain":{"ps":null}}}}}}},"hex":"3C6D6573736167652D626F64"},{"time":"1501099507","channel":"PCCH-Message","event":"paging","PCCH-Message":{"message":{"c1":{"paging":{"pagingRecordList":{"PagingRecord":{"ue-Identity":{"s-TMSI":{"mmec":"\n                                    00111000\n                                ","m-TMSI":"\n                                    11001011000111001010101100011111\n                                "}},"cn-Domain":{"ps":null}}}}}}},"hex":"3C6D6573736167652D626F64"},{"time":"1501099508","channel":"PCCH-Message","event":"paging","PCCH-Message":{"message":{"c1":{"paging":{"pagingRecordList":{"PagingRecord":{"ue-Identity":{"s-TMSI":{"mmec":"\n                                    00111000\n                                ","m-TMSI":"\n                                    11001011000111001010101100011111\n                                "}},"cn-Domain":{"ps":null}}}}}}},"hex":"3C6D6573736167652D626F64"},{"time":"1501099509","channel":"PCCH-Message","event":"paging","PCCH-Message":{"message":{"c1":{"paging":{"pagingRecordList":{"PagingRecord":{"ue-Identity":{"s-TMSI":{"mmec":"\n                                    00111000\n                                ","m-TMSI":"\n                                    11100010000101111101010111010001\n                                "}},"cn-Domain":{"ps":null}}}}}}},"hex":"3C6D6573736167652D626F64"},{"time":"1501099509","channel":"PCCH-Message","event":"paging","PCCH-Message":{"message":{"c1":{"paging":{"pagingRecordList":{"PagingRecord":{"ue-Identity":{"s-TMSI":{"mmec":"\n                                    00111000\n                                ","m-TMSI":"\n                                    11100010000101111101010111010001\n                                "}},"cn-Domain":{"ps":null}}}}}}},"hex":"3C6D6573736167652D626F64"},{"time":"1501099510","channel":"PCCH-Message","event":"paging","PCCH-Message":{"message":{"c1":{"paging":{"pagingRecordList":{"PagingRecord":[{"ue-Identity":{"s-TMSI":{"mmec":"\n                                    00111000\n                                ","m-TMSI":"\n                                    11010010000001011101010101110001\n                                "}},"cn-Domain":{"ps":null}},{"ue-Identity":{"s-TMSI":{"mmec":"\n                                    00111000\n                                ","m-TMSI":"\n                                    11000010000000000011100001001001\n                                "}},"cn-Domain":{"ps":null}},{"ue-Identity":{"s-TMSI":{"mmec":"\n                                    00111000\n                                ","m-TMSI":"\n                                    11010010000000000011011111010101\n                                "}},"cn-Domain":{"cs":null}}]}}}}},"hex":"3C6D6573736167652D626F64793E3C74696D653E31353031303939"},{"time":"1501099510","channel":"PCCH-Message","event":"paging","PCCH-Message":{"message":{"c1":{"paging":{"pagingRecordList":{"PagingRecord":{"ue-Identity":{"s-TMSI":{"mmec":"\n                                    00111000\n                                ","m-TMSI":"\n                                    11011000000111110100101111010111\n                                "}},"cn-Domain":{"ps":null}}}}}}},"hex":"3C6D6573736167652D626F64"},{"time":"1501099511","channel":"PCCH-Message","event":"paging","PCCH-Message":{"message":{"c1":{"paging":{"pagingRecordList":{"PagingRecord":{"ue-Identity":{"s-TMSI":{"mmec":"\n                                    00111000\n                                ","m-TMSI":"\n                                    11011000000111110100101111010111\n                                "}},"cn-Domain":{"ps":null}}}}}}},"hex":"3C6D6573736167652D626F64"},{"time":"1501099511","channel":"PCCH-Message","event":"paging","PCCH-Message":{"message":{"c1":{"paging":{"pagingRecordList":{"PagingRecord":[{"ue-Identity":{"s-TMSI":{"mmec":"\n                                    00111000\n                                ","m-TMSI":"\n                                    11000010000001111101010111011101\n                                "}},"cn-Domain":{"ps":null}},{"ue-Identity":{"s-TMSI":{"mmec":"\n                                    00100000\n                                ","m-TMSI":"\n                                    00111000110000100001100000001000\n                                "}},"cn-Domain":{"cs":null}}]}}}}},"hex":"3C6D6573736167652D626F64793E3C74696D65"},{"time":"1501099512","channel":"PCCH-Message","event":"paging","PCCH-Message":{"message":{"c1":{"paging":{"pagingRecordList":{"PagingRecord":{"ue-Identity":{"s-TMSI":{"mmec":"\n                                    00111000\n                                ","m-TMSI":"\n                                    11100010000001111011011001000100\n                                "}},"cn-Domain":{"ps":null}}}}}}},"hex":"3C6D6573736167652D626F64"},{"time":"1501099512","channel":"PCCH-Message","event":"paging","PCCH-Message":{"message":{"c1":{"paging":{"pagingRecordList":{"PagingRecord":{"ue-Identity":{"s-TMSI":{"mmec":"\n                                    00111000\n                                ","m-TMSI":"\n                                    11100010000001111011011001000100\n                                "}},"cn-Domain":{"ps":null}}}}}}},"hex":"3C6D6573736167652D626F64"},{"time":"1501099513","channel":"PCCH-Message","event":"paging","PCCH-Message":{"message":{"c1":{"paging":{"pagingRecordList":{"PagingRecord":{"ue-Identity":{"s-TMSI":{"mmec":"\n                                    00111000\n                                ","m-TMSI":"\n                                    11000010000110010100010011010011\n                                "}},"cn-Domain":{"ps":null}}}}}}},"hex":"3C6D6573736167652D626F64"},{"time":"1501099513","channel":"PCCH-Message","event":"paging","PCCH-Message":{"message":{"c1":{"paging":""}}},"hex":"3C6D65"},{"time":"1344751343","channel":"DL-DCCH-Message","event":"csfbParametersResponseCDMA2000","DL-DCCH-Message":{"message":{"c1":{"csfbParametersResponseCDMA2000":{"rrc-TransactionIdentifier":"0","criticalExtensions":{"csfbParametersResponseCDMA2000-r8":{"rand":"\n                            00000000000000000000000000000000\n                        ","mobilityParameters":""}}}}}},"hex":"3C6D6573736167652D62"},{"time":"1344751343","channel":"DL-DCCH-Message","event":"mobilityFromEUTRACommandMA2000","DL-DCCH-Message":{"message":{"c1":{"mobilityFromEUTRACommand":{"rrc-TransactionIdentifier":"1","criticalExtensions":{"criticalExtensionsFuture":""}}}}},"hex":"3C6D6573736167"},{"time":"1344751343","channel":"DL-DCCH-Message","event":"csfbParametersResponseCDMA2000","DL-DCCH-Message":{"message":{"c1":{"csfbParametersResponseCDMA2000":{"rrc-TransactionIdentifier":"0","criticalExtensions":{"csfbParametersResponseCDMA2000-r8":{"rand":"\n                            00000000000000000000000000000000\n                        ","mobilityParameters":""}}}}}},"hex":"3C6D6573736167652D62"},{"time":"1344751343","channel":"BCCH-DL-SCH-Message","event":"messageClassExtension","BCCH-DL-SCH-Message":{"message":{"messageClassExtension":""}},"hex":"3C6D65"},{"time":"1344751343","channel":"DL-DCCH-Messagesage","event":"csfbParametersResponseCDMA2000","DL-DCCH-Message":{"message":{"c1":{"csfbParametersResponseCDMA2000":{"rrc-TransactionIdentifier":"0","criticalExtensions":{"criticalExtensionsFuture":""}}}}},"hex":"3C6D6573736167"},{"time":"1344751425","channel":"DL-DCCH-Message","event":"mobilityFromEUTRACommandMA2000","DL-DCCH-Message":{"message":{"c1":{"mobilityFromEUTRACommand":{"rrc-TransactionIdentifier":"3","criticalExtensions":{"c1":{"spare1":""}}}}}},"hex":"3C6D6573736167"},{"time":"1344751425","channel":"DL-DCCH-Message","event":"csfbParametersResponseCDMA2000","DL-DCCH-Message":{"message":{"c1":{"csfbParametersResponseCDMA2000":{"rrc-TransactionIdentifier":"0","criticalExtensions":{"csfbParametersResponseCDMA2000-r8":{"rand":"\n                            00000000000000000000000000000000\n                        ","mobilityParameters":""}}}}}},"hex":"3C6D6573736167652D62"},{"time":"1344751425","channel":"DL-DCCH-Message","event":"csfbParametersResponseCDMA2000","DL-DCCH-Message":{"message":{"c1":{"csfbParametersResponseCDMA2000":{"rrc-TransactionIdentifier":"0","criticalExtensions":{"criticalExtensionsFuture":""}}}}},"hex":"3C6D6573736167"},{"time":"1501099514","channel":"PCCH-Message","event":"paging","PCCH-Message":{"message":{"c1":{"paging":{"pagingRecordList":{"PagingRecord":{"ue-Identity":{"s-TMSI":{"mmec":"\n                                    00111000\n                                ","m-TMSI":"\n                                    11100010000011000000101100010011\n                                "}},"cn-Domain":{"ps":null}}}}}}},"hex":"3C6D6573736167652D626F64"},{"time":"1501099515","channel":"PCCH-Message","event":"paging","PCCH-Message":{"message":{"c1":{"paging":{"pagingRecordList":{"PagingRecord":{"ue-Identity":{"s-TMSI":{"mmec":"\n                                    00111000\n                                ","m-TMSI":"\n                                    11001010000101111101010111011111\n                                "}},"cn-Domain":{"cs":null}}}}}}},"hex":"3C6D6573736167652D626F64"},{"time":"1501099516","channel":"PCCH-Message","event":"paging","PCCH-Message":{"message":{"c1":{"paging":{"pagingRecordList":{"PagingRecord":{"ue-Identity":{"s-TMSI":{"mmec":"\n                                    00111000\n                                ","m-TMSI":"\n                                    11000010000111010010010101100101\n                                "}},"cn-Domain":{"ps":null}}}}}}},"hex":"3C6D6573736167652D626F64"},{"time":"1344754654","channel":"DL-DCCH-Message","event":"csfbParametersResponseCDMA2000","DL-DCCH-Message":{"message":{"c1":{"csfbParametersResponseCDMA2000":{"rrc-TransactionIdentifier":"0","criticalExtensions":{"criticalExtensionsFuture":""}}}}},"hex":"3C6D6573736167"},{"time":"1501099516","channel":"PCCH-Message","event":"paging","PCCH-Message":{"message":{"c1":{"paging":{"pagingRecordList":{"PagingRecord":{"ue-Identity":{"s-TMSI":{"mmec":"\n                                    00111000\n                                ","m-TMSI":"\n                                    11000001000001110000000101100000\n                                "}},"cn-Domain":{"ps":null}}}}}}},"hex":"3C6D6573736167652D626F64"},{"time":"1501099517","channel":"PCCH-Message","event":"paging","PCCH-Message":{"message":{"c1":{"paging":{"pagingRecordList":{"PagingRecord":{"ue-Identity":{"s-TMSI":{"mmec":"\n                                    00111000\n                                ","m-TMSI":"\n                                    11000001000001110000000101100000\n                                "}},"cn-Domain":{"ps":null}}}}}}},"hex":"3C6D6573736167652D626F64"},{"time":"1344755062","channel":"DL-DCCH-Message","event":"ueInformationRequest-r9","DL-DCCH-Message":{"message":{"c1":{"ueInformationRequest-r9":{"rrc-TransactionIdentifier":"2","criticalExtensions":{"c1":{"spare1":""}}}}}},"hex":"3C6D6573736167"},{"time":"1501099518","channel":"PCCH-Message","event":"paging","PCCH-Message":{"message":{"c1":{"paging":{"pagingRecordList":{"PagingRecord":{"ue-Identity":{"s-TMSI":{"mmec":"\n                                    00111000\n                                ","m-TMSI":"\n                                    11100010000101100111110100010110\n                                "}},"cn-Domain":{"ps":null}}}}}}},"hex":"3C6D6573736167652D626F64"},{"time":"1501099519","channel":"PCCH-Message","event":"paging","PCCH-Message":{"message":{"c1":{"paging":{"pagingRecordList":{"PagingRecord":[{"ue-Identity":{"s-TMSI":{"mmec":"\n                                    00111000\n                                ","m-TMSI":"\n                                    11000010000110100001000100110000\n                                "}},"cn-Domain":{"ps":null}},{"ue-Identity":{"s-TMSI":{"mmec":"\n                                    00111000\n                                ","m-TMSI":"\n                                    11011101000000001011100110110101\n                                "}},"cn-Domain":{"ps":null}}]}}}}},"hex":"3C6D6573736167652D626F64793E3C74696D65"},{"time":"1501099519","channel":"PCCH-Message","event":"paging","PCCH-Message":{"message":{"c1":{"paging":{"pagingRecordList":{"PagingRecord":{"ue-Identity":{"s-TMSI":{"mmec":"\n                                    00111000\n                                ","m-TMSI":"\n                                    11001001000111111010000111100110\n                                "}},"cn-Domain":{"ps":null}}}}}}},"hex":"3C6D6573736167652D626F64"},{"time":"1501099519","channel":"BCCH-DL-SCH-Message","event":"systemInformationBlockType1","BCCH-DL-SCH-Message":{"message":{"c1":{"systemInformationBlockType1":{"cellAccessRelatedInfo":{"plmn-IdentityList":{"PLMN-IdentityInfo":{"plmn-Identity":{"mcc":{"MCC-MNC-Digit":["4","1","0"]},"mnc":{"MCC-MNC-Digit":["0","4"]}},"cellReservedForOperatorUse":{"notReserved":null}}},"trackingAreaCode":"\n                        1001110001001001\n                    ","cellIdentity":"\n                        0000000110001110010000000010\n                    ","cellBarred":{"notBarred":null},"intraFreqReselection":{"allowed":null},"csg-Indication":{"false":null}},"cellSelectionInfo":{"q-RxLevMin":"-64"},"freqBandIndicator":"3","schedulingInfoList":{"SchedulingInfo":[{"si-Periodicity":{"rf16":null},"sib-MappingInfo":{"sibType3":null}},{"si-Periodicity":{"rf32":null},"sib-MappingInfo":{"sibType5":null}},{"si-Periodicity":{"rf64":null},"sib-MappingInfo":{"sibType6":null}}]},"si-WindowLength":{"ms40":null},"systemInfoValueTag":"23"}}}},"hex":"3C6D6573736167652D626F64793E3C74696D653E313530313039393531393C2F74696D653E3C63"},{"time":"1501099519","channel":"BCCH-DL-SCH-Message","event":"systemInformation","BCCH-DL-SCH-Message":{"message":{"c1":{"systemInformation":{"criticalExtensions":{"systemInformation-r8":{"sib-TypeAndInfo":{"sib2":{"radioResourceConfigCommon":{"rach-ConfigCommon":{"preambleInfo":{"numberOfRA-Preambles":{"n52":null},"preamblesGroupAConfig":{"sizeOfRA-PreamblesGroupA":{"n28":null},"messageSizeGroupA":{"b56":null},"messagePowerOffsetGroupB":{"dB10":null}}},"powerRampingParameters":{"powerRampingStep":{"dB2":null},"preambleInitialReceivedTargetPower":{"dBm-104":null}},"ra-SupervisionInfo":{"preambleTransMax":{"n10":null},"ra-ResponseWindowSize":{"sf10":null},"mac-ContentionResolutionTimer":{"sf64":null}},"maxHARQ-Msg3Tx":"5"},"bcch-Config":{"modificationPeriodCoeff":{"n2":null}},"pcch-Config":{"defaultPagingCycle":{"rf32":null},"nB":{"oneT":null}},"prach-Config":{"rootSequenceIndex":"455","prach-ConfigInfo":{"prach-ConfigIndex":"4","highSpeedFlag":{"false":null},"zeroCorrelationZoneConfig":"10","prach-FreqOffset":"6"}},"pdsch-ConfigCommon":{"referenceSignalPower":"21","p-b":"1"},"pusch-ConfigCommon":{"pusch-ConfigBasic":{"n-SB":"4","hoppingMode":{"interSubFrame":null},"pusch-HoppingOffset":"22","enable64QAM":{"false":null}},"ul-ReferenceSignalsPUSCH":{"groupHoppingEnabled":{"false":null},"groupAssignmentPUSCH":"0","sequenceHoppingEnabled":{"false":null},"cyclicShift":"0"}},"pucch-ConfigCommon":{"deltaPUCCH-Shift":{"ds1":null},"nRB-CQI":"1","nCS-AN":"0","n1PUCCH-AN":"18"},"soundingRS-UL-ConfigCommon":{"release":""},"uplinkPowerControlCommon":{"p0-NominalPUSCH":"-67","alpha":{"al07":null},"p0-NominalPUCCH":"-102","deltaFList-PUCCH":{"deltaF-PUCCH-Format1":{"deltaF0":null},"deltaF-PUCCH-Format1b":{"deltaF3":null},"deltaF-PUCCH-Format2":{"deltaF1":null},"deltaF-PUCCH-Format2a":{"deltaF2":null},"deltaF-PUCCH-Format2b":{"deltaF2":null}},"deltaPreambleMsg3":"4"},"ul-CyclicPrefixLength":{"len1":null}},"ue-TimersAndConstants":{"t300":{"ms1000":null},"t301":{"ms200":null},"t310":{"ms1000":null},"n310":{"n10":null},"t311":{"ms10000":null},"n311":{"n1":null}},"freqInfo":{"ul-Bandwidth":{"n75":null},"additionalSpectrumEmission":"1"},"timeAlignmentTimerCommon":{"sf10240":null}},"sib3":{"cellReselectionInfoCommon":{"q-Hyst":{"dB4":null}},"cellReselectionServingFreqInfo":{"s-NonIntraSearch":"11","threshServingLow":"10","cellReselectionPriority":"7"},"intraFreqCellReselectionInfo":{"q-RxLevMin":"-64","s-IntraSearch":"29","presenceAntennaPort1":{"false":null},"neighCellConfig":"\n                                            01\n                                        ","t-ReselectionEUTRA":"1","t-ReselectionEUTRA-SF":{"sf-Medium":{"lDot0":null},"sf-High":{"oDot75":null}}},"s-IntraSearch-v920":{"s-IntraSearchP-r9":"29","s-IntraSearchQ-r9":"26"}}}}}}}}},"hex":"3C6D6573736167652D626F64793E3C74696D653E313530313039393531393C2F74696D653E3C6368616E6E656C3E424343482D444C2D5343482D4D6573736167653C2F6368616E6E656C3E3C6576656E743E73797374656D496E666F726D6174696F6E3C2F6576656E743E3C424343482D444C2D5343482D4D6573736167653E0A202020203C6D65"},{"time":"1501099519","channel":"BCCH-DL-SCH-Message","event":"systemInformation","BCCH-DL-SCH-Message":{"message":{"c1":{"systemInformation":{"criticalExtensions":{"systemInformation-r8":{"sib-TypeAndInfo":{"sib2":{"radioResourceConfigCommon":{"rach-ConfigCommon":{"preambleInfo":{"numberOfRA-Preambles":{"n52":null},"preamblesGroupAConfig":{"sizeOfRA-PreamblesGroupA":{"n28":null},"messageSizeGroupA":{"b56":null},"messagePowerOffsetGroupB":{"dB10":null}}},"powerRampingParameters":{"powerRampingStep":{"dB2":null},"preambleInitialReceivedTargetPower":{"dBm-104":null}},"ra-SupervisionInfo":{"preambleTransMax":{"n10":null},"ra-ResponseWindowSize":{"sf10":null},"mac-ContentionResolutionTimer":{"sf64":null}},"maxHARQ-Msg3Tx":"5"},"bcch-Config":{"modificationPeriodCoeff":{"n2":null}},"pcch-Config":{"defaultPagingCycle":{"rf32":null},"nB":{"oneT":null}},"prach-Config":{"rootSequenceIndex":"455","prach-ConfigInfo":{"prach-ConfigIndex":"4","highSpeedFlag":{"false":null},"zeroCorrelationZoneConfig":"10","prach-FreqOffset":"6"}},"pdsch-ConfigCommon":{"referenceSignalPower":"21","p-b":"1"},"pusch-ConfigCommon":{"pusch-ConfigBasic":{"n-SB":"4","hoppingMode":{"interSubFrame":null},"pusch-HoppingOffset":"22","enable64QAM":{"false":null}},"ul-ReferenceSignalsPUSCH":{"groupHoppingEnabled":{"false":null},"groupAssignmentPUSCH":"0","sequenceHoppingEnabled":{"false":null},"cyclicShift":"0"}},"pucch-ConfigCommon":{"deltaPUCCH-Shift":{"ds1":null},"nRB-CQI":"1","nCS-AN":"0","n1PUCCH-AN":"18"},"soundingRS-UL-ConfigCommon":{"release":""},"uplinkPowerControlCommon":{"p0-NominalPUSCH":"-67","alpha":{"al07":null},"p0-NominalPUCCH":"-102","deltaFList-PUCCH":{"deltaF-PUCCH-Format1":{"deltaF0":null},"deltaF-PUCCH-Format1b":{"deltaF3":null},"deltaF-PUCCH-Format2":{"deltaF1":null},"deltaF-PUCCH-Format2a":{"deltaF2":null},"deltaF-PUCCH-Format2b":{"deltaF2":null}},"deltaPreambleMsg3":"4"},"ul-CyclicPrefixLength":{"len1":null}},"ue-TimersAndConstants":{"t300":{"ms1000":null},"t301":{"ms200":null},"t310":{"ms1000":null},"n310":{"n10":null},"t311":{"ms10000":null},"n311":{"n1":null}},"freqInfo":{"ul-Bandwidth":{"n75":null},"additionalSpectrumEmission":"1"},"timeAlignmentTimerCommon":{"sf10240":null}},"sib3":{"cellReselectionInfoCommon":{"q-Hyst":{"dB4":null}},"cellReselectionServingFreqInfo":{"s-NonIntraSearch":"11","threshServingLow":"10","cellReselectionPriority":"7"},"intraFreqCellReselectionInfo":{"q-RxLevMin":"-64","s-IntraSearch":"29","presenceAntennaPort1":{"false":null},"neighCellConfig":"\n                                            01\n                                        ","t-ReselectionEUTRA":"1","t-ReselectionEUTRA-SF":{"sf-Medium":{"lDot0":null},"sf-High":{"oDot75":null}}},"s-IntraSearch-v920":{"s-IntraSearchP-r9":"29","s-IntraSearchQ-r9":"26"}}}}}}}}},"hex":"3C6D6573736167652D626F64793E3C74696D653E313530313039393531393C2F74696D653E3C6368616E6E656C3E424343482D444C2D5343482D4D6573736167653C2F6368616E6E656C3E3C6576656E743E73797374656D496E666F726D6174696F6E3C2F6576656E743E3C424343482D444C2D5343482D4D6573736167653E0A202020203C6D65"},{"time":"1501099519","channel":"BCCH-DL-SCH-Message","event":"systemInformationBlockType1","BCCH-DL-SCH-Message":{"message":{"c1":{"systemInformationBlockType1":{"cellAccessRelatedInfo":{"plmn-IdentityList":{"PLMN-IdentityInfo":{"plmn-Identity":{"mcc":{"MCC-MNC-Digit":["4","1","0"]},"mnc":{"MCC-MNC-Digit":["0","4"]}},"cellReservedForOperatorUse":{"notReserved":null}}},"trackingAreaCode":"\n                        1001110001001001\n                    ","cellIdentity":"\n                        0000000110001110010000000010\n                    ","cellBarred":{"notBarred":null},"intraFreqReselection":{"allowed":null},"csg-Indication":{"false":null}},"cellSelectionInfo":{"q-RxLevMin":"-64"},"freqBandIndicator":"3","schedulingInfoList":{"SchedulingInfo":[{"si-Periodicity":{"rf16":null},"sib-MappingInfo":{"sibType3":null}},{"si-Periodicity":{"rf32":null},"sib-MappingInfo":{"sibType5":null}},{"si-Periodicity":{"rf64":null},"sib-MappingInfo":{"sibType6":null}}]},"si-WindowLength":{"ms40":null},"systemInfoValueTag":"23"}}}},"hex":"3C6D6573736167652D626F64793E3C74696D653E313530313039393531393C2F74696D653E3C63"},{"time":"1501099519","channel":"BCCH-DL-SCH-Message","event":"systemInformation","BCCH-DL-SCH-Message":{"message":{"c1":{"systemInformation":{"criticalExtensions":{"systemInformation-r8":{"sib-TypeAndInfo":{"sib5":{"interFreqCarrierFreqList":{"InterFreqCarrierFreqInfo":{"dl-CarrierFreq":"1632","q-RxLevMin":"-64","t-ReselectionEUTRA":"1","threshX-High":"11","threshX-Low":"11","allowedMeasBandwidth":{"mbw75":null},"presenceAntennaPort1":{"false":null},"neighCellConfig":"\n                                                01\n                                            ","q-OffsetFreq":{"dB0":null}}}}}}}}}}},"hex":"3C6D6573736167652D626F64793E3C74696D653E31353031"},{"time":"1501099520","channel":"BCCH-DL-SCH-Message","event":"systemInformation","BCCH-DL-SCH-Message":{"message":{"c1":{"systemInformation":{"criticalExtensions":{"systemInformation-r8":{"sib-TypeAndInfo":{"sib6":{"carrierFreqListUTRA-FDD":{"CarrierFreqUTRA-FDD":[{"carrierFreq":"10562","cellReselectionPriority":"6","threshX-High":"4","threshX-Low":"5","q-RxLevMin":"-55","p-MaxUTRA":"24","q-QualMin":"-22"},{"carrierFreq":"10587","cellReselectionPriority":"6","threshX-High":"4","threshX-Low":"5","q-RxLevMin":"-55","p-MaxUTRA":"24","q-QualMin":"-22"},{"carrierFreq":"10712","cellReselectionPriority":"6","threshX-High":"4","threshX-Low":"5","q-RxLevMin":"-55","p-MaxUTRA":"24","q-QualMin":"-22"}]},"t-ReselectionUTRA":"4"}}}}}}}},"hex":"3C6D6573736167652D626F64793E3C74696D653E313530313039393532303C2F74696D653E3C6368"},{"time":"1501099520","channel":"PCCH-Messageation","event":"paging","PCCH-Message":{"message":{"c1":{"paging":{"pagingRecordList":{"PagingRecord":{"ue-Identity":{"s-TMSI":{"mmec":"\n                                    00111000\n                                ","m-TMSI":"\n                                    11110010000001111000011000100010\n                                "}},"cn-Domain":{"ps":null}}}}}}},"hex":"3C6D6573736167652D626F64"},{"time":"1501099521","channel":"UL-DCCH-Message","event":"ulHandoverPreparationTransfer","UL-DCCH-Message":{"message":{"c1":{"ulHandoverPreparationTransfer":{"criticalExtensions":{"c1":{"spare3":""}}}}}},"hex":"3C6D65737361"},{"time":"1344756128","channel":"DL-DCCH-Message","event":"csfbParametersResponseCDMA2000","DL-DCCH-Message":{"message":{"c1":{"csfbParametersResponseCDMA2000":{"rrc-TransactionIdentifier":"0","criticalExtensions":{"criticalExtensionsFuture":""}}}}},"hex":"3C6D6573736167"},{"time":"1501099522","channel":"PCCH-Message","event":"paging","PCCH-Message":{"message":{"c1":{"paging":{"pagingRecordList":{"PagingRecord":{"ue-Identity":{"s-TMSI":{"mmec":"\n                                    00111000\n                                ","m-TMSI":"\n                                    11000010000001000101010101110111\n                                "}},"cn-Domain":{"ps":null}}}}}}},"hex":"3C6D6573736167652D626F64"},{"time":"1501099522","channel":"PCCH-Message","event":"paging","PCCH-Message":{"message":{"c1":{"paging":{"pagingRecordList":{"PagingRecord":{"ue-Identity":{"s-TMSI":{"mmec":"\n                                    00111000\n                                ","m-TMSI":"\n                                    11000010000001000101010101110111\n                                "}},"cn-Domain":{"ps":null}}}}}}},"hex":"3C6D6573736167652D626F64"},{"time":"1501099523","channel":"PCCH-Message","event":"paging","PCCH-Message":{"message":{"c1":{"paging":{"pagingRecordList":{"PagingRecord":{"ue-Identity":{"s-TMSI":{"mmec":"\n                                    00111000\n                                ","m-TMSI":"\n                                    11000010000001000101010101110111\n                                "}},"cn-Domain":{"ps":null}}}}}}},"hex":"3C6D6573736167652D626F64"},{"time":"1501099523","channel":"UL-CCCH-Message","event":"rrcConnectionRequest","UL-CCCH-Message":{"message":{"c1":{"rrcConnectionRequest":{"criticalExtensions":{"rrcConnectionRequest-r8":{"ue-Identity":{"s-TMSI":{"mmec":"\n                                    00011000\n                                ","m-TMSI":"\n                                    10010000000100000000000000000000\n                                "}},"establishmentCause":{"emergency":null},"spare":"\n                            0\n                        "}}}}}},"hex":"3C6D6573736167652D626F64793E"},{"time":"1501099523","channel":"PCCH-Message","event":"paging","PCCH-Message":{"message":{"c1":{"paging":""}}},"hex":"3C6D65"}]}}
